{
    "pageIndex": 1,
    "pageSize": 25,
    "totalCount": 83,
    "totalPages": 4,
    "hasPreviousPage": false,
    "hasNextPage": true,
    "items": [
        {
            "createdName": "",
            "modifiedName": "Vikas Patel",
            "domainName": "https://beta-cg.parsonskellogg.shop/",
            "id": 122,
            "title": "Custom Sports Apparel that Works Hard to Outperform Your Competitors",
            "pageType": "Blog",
            "passRequired": null,
            "password": "",
            "passExpiryPeriod": null,
            "tag": "",
            "author": "Super Admin",
            "previewAs": "",
            "storeId": 5,
            "slug": "custom-sports-apparel",
            "topicTitle": "test Custom Sports Apparel + Your Logo – Corporate Gear",
            "metaDescription": "test Corporate Gear offers custom-embroidered corporate apparel, branded clothing, & accessories. Get YOUR logo printed on top-tier brands. Order today!",
            "metaKeywords": "test custom sports apparel, sports apparel",
            "templateId": 0,
            "headHtml": "",
            "footerhtml": "",
            "canonicalurl": "",
            "publishDuration": "P",
            "publishDate": "2024-10-10T05:55:24.28947",
            "publishTime": "2024-10-10T09:52:38.097",
            "unpublishDate": null,
            "unpublishTime": null,
            "scheduleUnpublish": "",
            "redirectPageId": null,
            "createdBy": null,
            "updatedBy": "14",
            "status": "P",
            "createdAt": "2022-03-13T11:57:17",
            "updatedAT": "2024-10-10T10:04:49.922",
            "isHomePage": "N",
            "publish_status": "Y",
            "menuType": "",
            "oldId": null,
            "storiesImage": null,
            "categoryId": 0,
            "displaySideBar": null,
            "description": null,
            "productSku": "[{\"name\":\"Custom Nike (Everything)\",\"link\":\"https://www.corporategear.com/nike.html?v=brand-product-list\",\"buttonText\":\"SHOP NOW\",\"image\":\"/storagemedia/temp/1/content/122/productimage/64c71518-6f2b-4fa3-bf26-54daff5324be.png\"},{\"name\":\"Peter Millar Golf\",\"link\":\"https://www.corporategear.com/peter-millar.html?v=brand-product-list\",\"buttonText\":\"SHOP NOW\",\"image\":\"/storagemedia/temp/1/content/122/productimage/27b32633-16bf-4fb6-aac7-86a6bce90681.png\"},{\"name\":\"Customize Under Armour\",\"link\":\"https://www.corporategear.com/under-armour.html?sort=&v=brand-product-list\",\"buttonText\":\"SHOP NOW\",\"image\":\"/storagemedia/temp/1/content/122/productimage/1ca7c862-56fa-4e7a-a549-575039130eae.png\"},{\"name\":\"Branded Adidas\",\"link\":\"https://www.corporategear.com/adidas.html?sort=&v=brand-product-list\",\"buttonText\":\"SHOP NOW\",\"image\":\"/storagemedia/temp/1/content/122/productimage/1fba6bc4-3e4e-4513-bf12-417656848fce.png\"}]",
            "isbreadcrumbShow": "Y",
            "isonSitemap": false,
            "parentId": 0,
            "openGraphImagePath": null,
            "openGraphTitle": null,
            "openGraphDescription": null,
            "facebookImagePath": null,
            "facebookOpenGraphTitle": null,
            "facebookOpenGraphDescription": null,
            "twitterImagePath": null,
            "twitterOpenGraphTitle": null,
            "twitterOpenGraphDescription": null,
            "linkedinImagePath": null,
            "linkedinOpenGraphTitle": null,
            "linkedinOpenGraphDescription": null,
            "pinterestImagePath": null,
            "pinterestOpenGraphTitle": null,
            "pinterestOpenGraphDescription": null,
            "isNewStructure": true
        },
        {
            "createdName": "",
            "modifiedName": "Tejas Daftary",
            "domainName": "https://beta-cg.parsonskellogg.shop/",
            "id": 123,
            "title": "Southern Tide Company Logo Clothing",
            "pageType": "Blog",
            "passRequired": null,
            "password": "",
            "passExpiryPeriod": null,
            "tag": "Blog, Story, Article",
            "author": "",
            "previewAs": "",
            "storeId": 5,
            "slug": "southern-tide-company-logo-clothing",
            "topicTitle": "Southern Tide Company Logo Clothing",
            "metaDescription": "Corporate Gear offers custom-embroidered corporate apparel, branded clothing, & accessories. Get YOUR logo printed on top-tier brands. Order today!",
            "metaKeywords": "Corporate Merch, Custom Apparel, Corporate Gifts, Corporate Gear, Corporate Gifting",
            "templateId": 0,
            "headHtml": "",
            "footerhtml": "",
            "canonicalurl": "",
            "publishDuration": "D",
            "publishDate": "2024-10-10T05:11:48.1273709",
            "publishTime": null,
            "unpublishDate": null,
            "unpublishTime": null,
            "scheduleUnpublish": null,
            "redirectPageId": null,
            "createdBy": null,
            "updatedBy": "105",
            "status": "P",
            "createdAt": "2022-03-13T11:54:57",
            "updatedAT": "2024-10-10T05:11:45.6328014",
            "isHomePage": "N",
            "publish_status": null,
            "menuType": "",
            "oldId": null,
            "storiesImage": null,
            "categoryId": 0,
            "displaySideBar": null,
            "description": null,
            "productSku": "[]",
            "isbreadcrumbShow": "N",
            "isonSitemap": false,
            "parentId": 0,
            "openGraphImagePath": null,
            "openGraphTitle": null,
            "openGraphDescription": null,
            "facebookImagePath": null,
            "facebookOpenGraphTitle": null,
            "facebookOpenGraphDescription": null,
            "twitterImagePath": null,
            "twitterOpenGraphTitle": null,
            "twitterOpenGraphDescription": null,
            "linkedinImagePath": null,
            "linkedinOpenGraphTitle": null,
            "linkedinOpenGraphDescription": null,
            "pinterestImagePath": null,
            "pinterestOpenGraphTitle": null,
            "pinterestOpenGraphDescription": null,
            "isNewStructure": false
        },
        {
            "createdName": "",
            "modifiedName": "",
            "domainName": "https://beta-cg.parsonskellogg.shop/",
            "id": 389,
            "title": "Pantone Colors & the Important Role they Play in Co-Branding",
            "pageType": "Blog",
            "passRequired": null,
            "password": "",
            "passExpiryPeriod": null,
            "tag": "",
            "author": "",
            "previewAs": "",
            "storeId": 5,
            "slug": "pantone-colors-the-important-role-they-play-in-co-branding",
            "topicTitle": "Corporate Gear",
            "metaDescription": "Corporate Gear",
            "metaKeywords": "Corporate Gear",
            "templateId": 0,
            "headHtml": "",
            "footerhtml": "",
            "canonicalurl": "",
            "publishDuration": null,
            "publishDate": null,
            "publishTime": null,
            "unpublishDate": null,
            "unpublishTime": null,
            "scheduleUnpublish": null,
            "redirectPageId": null,
            "createdBy": null,
            "updatedBy": null,
            "status": "P",
            "createdAt": "2022-03-10T12:18:55",
            "updatedAT": "2022-03-10T12:18:55",
            "isHomePage": "N",
            "publish_status": null,
            "menuType": "",
            "oldId": null,
            "storiesImage": null,
            "categoryId": 0,
            "displaySideBar": null,
            "description": null,
            "productSku": "[{\"name\":\"Nike Game Royal Men's Core Cotton T-Shirt\",\"link\":\"https://www.corporategear.com/nike-game-royal-men-core-cotton-t-shirt-nkbq5233.html\",\"buttonText\":\"SHOP NOW\",\"image\":\"/storagemedia/temp/1/content/389/productimage/56a8d78a-94d9-42d0-8ace-402e37434858.jpg\"},{\"name\":\"Nike Dri-FIT Scoop Neck T-Shirt Anthracite Women's\",\"link\":\"https://www.corporategear.com/nike-dri-fit-scoop-neck-t-shirt-anthracite-women-nkbq5234.html\",\"buttonText\":\"SHOP NOW\",\"image\":\"/storagemedia/temp/1/content/389/productimage/f056e7ea-9087-4330-8c97-35149f0a3725.jpg\"},{\"name\":\"Men's Red / White Under Armour Hustle Fleece Hoodie\",\"link\":\"https://www.corporategear.com/men-red-white-under-armour-hustle-fleece-hoodie-1300123.html\",\"buttonText\":\"SHOP NOW\",\"image\":\"/storagemedia/temp/1/content/389/productimage/68401bc2-62b3-41bc-8fe4-1b1399207090.jpg\"},{\"name\":\"Under Armour Women's Black / White Hustle Fleece Hoodie\",\"link\":\"https://www.corporategear.com/under-armour-women-black-white-hustle-fleece-hoodie-1300261.html\",\"buttonText\":\"SHOP NOW\",\"image\":\"/storagemedia/temp/1/content/389/productimage/0e9546a9-14db-40ad-95b0-6fde958e37fc.jpg\"}]",
            "isbreadcrumbShow": "false",
            "isonSitemap": false,
            "parentId": 0,
            "openGraphImagePath": null,
            "openGraphTitle": null,
            "openGraphDescription": null,
            "facebookImagePath": null,
            "facebookOpenGraphTitle": null,
            "facebookOpenGraphDescription": null,
            "twitterImagePath": null,
            "twitterOpenGraphTitle": null,
            "twitterOpenGraphDescription": null,
            "linkedinImagePath": null,
            "linkedinOpenGraphTitle": null,
            "linkedinOpenGraphDescription": null,
            "pinterestImagePath": null,
            "pinterestOpenGraphTitle": null,
            "pinterestOpenGraphDescription": null,
            "isNewStructure": false
        },
        {
            "createdName": "",
            "modifiedName": "",
            "domainName": "https://beta-cg.parsonskellogg.shop/",
            "id": 390,
            "title": "A North Face Fleece Jacket Increases Brand Visibility",
            "pageType": "Blog",
            "passRequired": null,
            "password": "",
            "passExpiryPeriod": null,
            "tag": "",
            "author": "",
            "previewAs": "",
            "storeId": 5,
            "slug": "a-north-face-fleece-jacket-increases-brand-visibility",
            "topicTitle": "Corporate Gear",
            "metaDescription": "Corporate Gear",
            "metaKeywords": "Corporate Gear",
            "templateId": 0,
            "headHtml": "",
            "footerhtml": "",
            "canonicalurl": "",
            "publishDuration": null,
            "publishDate": null,
            "publishTime": null,
            "unpublishDate": null,
            "unpublishTime": null,
            "scheduleUnpublish": null,
            "redirectPageId": null,
            "createdBy": null,
            "updatedBy": null,
            "status": "P",
            "createdAt": "2022-03-11T05:37:22",
            "updatedAT": "2022-03-11T05:37:22",
            "isHomePage": "N",
            "publish_status": null,
            "menuType": null,
            "oldId": null,
            "storiesImage": null,
            "categoryId": 0,
            "displaySideBar": null,
            "description": null,
            "productSku": null,
            "isbreadcrumbShow": null,
            "isonSitemap": false,
            "parentId": 0,
            "openGraphImagePath": null,
            "openGraphTitle": null,
            "openGraphDescription": null,
            "facebookImagePath": null,
            "facebookOpenGraphTitle": null,
            "facebookOpenGraphDescription": null,
            "twitterImagePath": null,
            "twitterOpenGraphTitle": null,
            "twitterOpenGraphDescription": null,
            "linkedinImagePath": null,
            "linkedinOpenGraphTitle": null,
            "linkedinOpenGraphDescription": null,
            "pinterestImagePath": null,
            "pinterestOpenGraphTitle": null,
            "pinterestOpenGraphDescription": null,
            "isNewStructure": false
        },
        {
            "createdName": "",
            "modifiedName": "",
            "domainName": "https://beta-cg.parsonskellogg.shop/",
            "id": 391,
            "title": "Successful Brand Partnerships Target Audiences with Strong Brand Affinity",
            "pageType": "Blog",
            "passRequired": null,
            "password": "",
            "passExpiryPeriod": null,
            "tag": "",
            "author": "",
            "previewAs": "",
            "storeId": 5,
            "slug": "successful-brand-partnerships-target-audiences-with-strong-brand-affinity",
            "topicTitle": "Corporate Gear",
            "metaDescription": "Corporate Gear",
            "metaKeywords": "Corporate Gear",
            "templateId": 0,
            "headHtml": "",
            "footerhtml": "",
            "canonicalurl": "",
            "publishDuration": null,
            "publishDate": null,
            "publishTime": null,
            "unpublishDate": null,
            "unpublishTime": null,
            "scheduleUnpublish": null,
            "redirectPageId": null,
            "createdBy": null,
            "updatedBy": null,
            "status": "P",
            "createdAt": "2022-03-12T09:08:17",
            "updatedAT": "2022-03-12T09:08:17",
            "isHomePage": "N",
            "publish_status": null,
            "menuType": "",
            "oldId": null,
            "storiesImage": null,
            "categoryId": 0,
            "displaySideBar": null,
            "description": null,
            "productSku": "[{\"name\":\"Helly Hansen Men's Black Kensington Hooded Softshell Jacket\",\"link\":\"https://www.corporategear.com/helly-hansen-men-black-kensington-hooded-softshell-jacket-74230.html\",\"buttonText\":\"START CUSTOMIZING\",\"image\":\"/storagemedia/temp/1/content/391/productimage/6a452124-49ef-4ef8-9e9d-c29ccedddb36.jpg\"},{\"name\":\"Helly Hansen Men's Ebony Quick-Dry Half-Zip\",\"link\":\"https://www.corporategear.com/helly-hansen-men-ebony-quick-dry-half-zip-30208.html\",\"buttonText\":\"START CUSTOMIZING\",\"image\":\"/storagemedia/temp/1/content/391/productimage/61c3605a-2968-4542-965a-e839f5493013.jpg\"},{\"name\":\"Helly Hansen Women's Daybreaker Fleece Navy\",\"link\":\"https://www.corporategear.com/helly-hansen-women-daybreaker-fleece-navy-51599.html\",\"buttonText\":\"START CUSTOMIZING\",\"image\":\"/storagemedia/temp/1/content/391/productimage/ad693a0f-0d26-4ad7-9d1c-1c983c8e6408.jpg\"},{\"name\":\"Helly Hansen Women's Black Manchester 2.0 Softshell Vest\",\"link\":\"https://www.corporategear.com/helly-hansen-women-black-manchester-2-0-softshell-vest-74242.html\",\"buttonText\":\"START CUSTOMIZING\",\"image\":\"/storagemedia/temp/1/content/391/productimage/1f695df2-6bc0-4a59-b242-a75f796701e7.jpg\"}]",
            "isbreadcrumbShow": "false",
            "isonSitemap": false,
            "parentId": 0,
            "openGraphImagePath": null,
            "openGraphTitle": null,
            "openGraphDescription": null,
            "facebookImagePath": null,
            "facebookOpenGraphTitle": null,
            "facebookOpenGraphDescription": null,
            "twitterImagePath": null,
            "twitterOpenGraphTitle": null,
            "twitterOpenGraphDescription": null,
            "linkedinImagePath": null,
            "linkedinOpenGraphTitle": null,
            "linkedinOpenGraphDescription": null,
            "pinterestImagePath": null,
            "pinterestOpenGraphTitle": null,
            "pinterestOpenGraphDescription": null,
            "isNewStructure": false
        },
        {
            "createdName": "",
            "modifiedName": "",
            "domainName": "https://beta-cg.parsonskellogg.shop/",
            "id": 392,
            "title": "Personalized Jackets that Promote Your Brand",
            "pageType": "Blog",
            "passRequired": null,
            "password": "",
            "passExpiryPeriod": null,
            "tag": "",
            "author": "",
            "previewAs": "",
            "storeId": 5,
            "slug": "personalized-jackets",
            "topicTitle": "Corporate Gear",
            "metaDescription": "Corporate Gear offers custom-embroidered corporate apparel, branded clothing, & accessories. Get YOUR logo printed on top-tier brands. Order today!",
            "metaKeywords": "Corporate Gear",
            "templateId": 0,
            "headHtml": "",
            "footerhtml": "",
            "canonicalurl": "",
            "publishDuration": null,
            "publishDate": null,
            "publishTime": null,
            "unpublishDate": null,
            "unpublishTime": null,
            "scheduleUnpublish": null,
            "redirectPageId": null,
            "createdBy": null,
            "updatedBy": null,
            "status": "P",
            "createdAt": "2022-03-12T09:40:57",
            "updatedAT": "2022-03-12T09:40:57",
            "isHomePage": "N",
            "publish_status": null,
            "menuType": "",
            "oldId": null,
            "storiesImage": null,
            "categoryId": 0,
            "displaySideBar": null,
            "description": null,
            "productSku": "[{\"name\":\"Men's Custom Jackets\",\"link\":\"https://www.corporategear.com/men-jackets.html?v=product-list\",\"buttonText\":\"START CUSTOMIZING\",\"image\":\"/storagemedia/temp/1/content/392/productimage/1b633334-ccec-46b5-a172-483ada9dad2e.jpg\"},{\"name\":\"Women's Custom Jackets\",\"link\":\"https://www.corporategear.com/women-jackets.html?v=product-list\",\"buttonText\":\"START CUSTOMIZING\",\"image\":\"/storagemedia/temp/1/content/392/productimage/d6a20ca3-3905-423e-aca6-f099b419491b.jpg\"}]",
            "isbreadcrumbShow": "false",
            "isonSitemap": false,
            "parentId": 0,
            "openGraphImagePath": null,
            "openGraphTitle": null,
            "openGraphDescription": null,
            "facebookImagePath": null,
            "facebookOpenGraphTitle": null,
            "facebookOpenGraphDescription": null,
            "twitterImagePath": null,
            "twitterOpenGraphTitle": null,
            "twitterOpenGraphDescription": null,
            "linkedinImagePath": null,
            "linkedinOpenGraphTitle": null,
            "linkedinOpenGraphDescription": null,
            "pinterestImagePath": null,
            "pinterestOpenGraphTitle": null,
            "pinterestOpenGraphDescription": null,
            "isNewStructure": false
        },
        {
            "createdName": "",
            "modifiedName": "",
            "domainName": "https://beta-cg.parsonskellogg.shop/",
            "id": 393,
            "title": "Gifts for Nurses and Your Healthcare Facility",
            "pageType": "Blog",
            "passRequired": null,
            "password": "",
            "passExpiryPeriod": null,
            "tag": "",
            "author": "",
            "previewAs": "",
            "storeId": 5,
            "slug": "gifts-for-nurses",
            "topicTitle": "Corporate Gear",
            "metaDescription": "Corporate Gear",
            "metaKeywords": "Corporate Gear",
            "templateId": 0,
            "headHtml": "",
            "footerhtml": "",
            "canonicalurl": "",
            "publishDuration": null,
            "publishDate": null,
            "publishTime": null,
            "unpublishDate": null,
            "unpublishTime": null,
            "scheduleUnpublish": null,
            "redirectPageId": null,
            "createdBy": null,
            "updatedBy": null,
            "status": "P",
            "createdAt": "2022-03-12T09:45:23",
            "updatedAT": "2022-03-12T09:45:23",
            "isHomePage": "N",
            "publish_status": null,
            "menuType": "",
            "oldId": null,
            "storiesImage": null,
            "categoryId": 0,
            "displaySideBar": null,
            "description": null,
            "productSku": "[{\"name\":\"Patagonia Micro D Quarter-Zip Women's Birch White\",\"link\":\"https://www.corporategear.com/patagonia-micro-d-quarter-zip-women-birch-white-26278.html\",\"buttonText\":\"SHOP NOW\",\"image\":\"/storagemedia/temp/1/content/393/productimage/d9e3ecc6-a2f0-4125-b154-e4520020aba6.jpg\"},{\"name\":\"Patagonia Men's Black Nano Puff Vest\",\"link\":\"https://www.corporategear.com/patagonia-men-black-nano-puff-vest-84242.html\",\"buttonText\":\"SHOP NOW\",\"image\":\"/storagemedia/temp/1/content/393/productimage/a86127f0-9e41-4f13-a9d2-5c2ce49c142c.jpg\"},{\"name\":\"YETI Rambler 20 oz Tumbler Black\",\"link\":\"https://www.corporategear.com/yeti-rambler-20-oz-tumbler-black-yram20.html\",\"buttonText\":\"SHOP NOW\",\"image\":\"/storagemedia/temp/1/content/393/productimage/70fbdcc5-df2d-46c1-9a81-3bbbf2168c39.jpg\"},{\"name\":\"Nike Dri-FIT Stretch Half-Zip Women's White / Dark Grey\",\"link\":\"https://www.corporategear.com/nike-dri-fit-stretch-half-zip-women-white-dark-grey-779796.html\",\"buttonText\":\"SHOP NOW\",\"image\":\"/storagemedia/temp/1/content/393/productimage/32560fc6-37ce-453b-b1b5-38f1a4003680.jpg\"}]",
            "isbreadcrumbShow": "false",
            "isonSitemap": false,
            "parentId": 0,
            "openGraphImagePath": null,
            "openGraphTitle": null,
            "openGraphDescription": null,
            "facebookImagePath": null,
            "facebookOpenGraphTitle": null,
            "facebookOpenGraphDescription": null,
            "twitterImagePath": null,
            "twitterOpenGraphTitle": null,
            "twitterOpenGraphDescription": null,
            "linkedinImagePath": null,
            "linkedinOpenGraphTitle": null,
            "linkedinOpenGraphDescription": null,
            "pinterestImagePath": null,
            "pinterestOpenGraphTitle": null,
            "pinterestOpenGraphDescription": null,
            "isNewStructure": false
        },
        {
            "createdName": "",
            "modifiedName": "",
            "domainName": "https://beta-cg.parsonskellogg.shop/",
            "id": 394,
            "title": "Corporate Logo Apparel From Top Premium Brands",
            "pageType": "Blog",
            "passRequired": null,
            "password": "",
            "passExpiryPeriod": null,
            "tag": "",
            "author": "",
            "previewAs": "",
            "storeId": 5,
            "slug": "corporate-logo-apparel",
            "topicTitle": "Corporate Gear",
            "metaDescription": "Corporate Gear",
            "metaKeywords": "Corporate Gear",
            "templateId": 0,
            "headHtml": "",
            "footerhtml": "",
            "canonicalurl": "",
            "publishDuration": null,
            "publishDate": null,
            "publishTime": null,
            "unpublishDate": null,
            "unpublishTime": null,
            "scheduleUnpublish": null,
            "redirectPageId": null,
            "createdBy": null,
            "updatedBy": null,
            "status": "P",
            "createdAt": "2022-03-12T09:48:41",
            "updatedAT": "2022-03-12T09:48:41",
            "isHomePage": "N",
            "publish_status": null,
            "menuType": "",
            "oldId": null,
            "storiesImage": null,
            "categoryId": 0,
            "displaySideBar": null,
            "description": null,
            "productSku": "[{\"name\":\"Men's Scarlet Nike Dri-FIT Showtime Hoodie\",\"link\":\"https://www.corporategear.com/men-scarlet-nike-dri-fit-showtime-hoodie-cq0306.html\",\"buttonText\":\"SHOP NOW\",\"image\":\"/storagemedia/temp/1/content/394/productimage/24464e7e-357c-4c1c-8028-4b4ccfeeddf9.jpg\"},{\"name\":\"Nike Cool Grey Dri-FIT Vertical Mesh Polo Men's\",\"link\":\"https://www.corporategear.com/nike-cool-grey-dri-fit-vertical-mesh-polo-men-637167.html\",\"buttonText\":\"SHOP NOW\",\"image\":\"/storagemedia/temp/1/content/394/productimage/c1fd9c01-9c52-4183-b79b-aa2845bf0967.jpg\"},{\"name\":\"Helly Hansen Women's Crew Vest Navy\",\"link\":\"https://www.corporategear.com/helly-hansen-women-crew-vest-navy-30290.html\",\"buttonText\":\"SHOP NOW\",\"image\":\"/storagemedia/temp/1/content/394/productimage/e4308a81-6983-42b7-b936-d73478037c04.jpg\"},{\"name\":\"Helly Hansen Women's Black Alphelia Jacket\",\"link\":\"https://www.corporategear.com/helly-hansen-women-black-alphelia-jacket-65909.html\",\"buttonText\":\"SHOP NOW\",\"image\":\"/storagemedia/temp/1/content/394/productimage/047fe8ad-f79d-424c-8a11-dc89ea7e24ec.jpg\"}]",
            "isbreadcrumbShow": "false",
            "isonSitemap": false,
            "parentId": 0,
            "openGraphImagePath": null,
            "openGraphTitle": null,
            "openGraphDescription": null,
            "facebookImagePath": null,
            "facebookOpenGraphTitle": null,
            "facebookOpenGraphDescription": null,
            "twitterImagePath": null,
            "twitterOpenGraphTitle": null,
            "twitterOpenGraphDescription": null,
            "linkedinImagePath": null,
            "linkedinOpenGraphTitle": null,
            "linkedinOpenGraphDescription": null,
            "pinterestImagePath": null,
            "pinterestOpenGraphTitle": null,
            "pinterestOpenGraphDescription": null,
            "isNewStructure": false
        },
        {
            "createdName": "",
            "modifiedName": "",
            "domainName": "https://beta-cg.parsonskellogg.shop/",
            "id": 401,
            "title": "Branded Nike Markets Your Business Beyond Any Metric",
            "pageType": "Blog",
            "passRequired": null,
            "password": "",
            "passExpiryPeriod": null,
            "tag": "",
            "author": "Super Admin",
            "previewAs": "",
            "storeId": 5,
            "slug": "branded-nike",
            "topicTitle": "Corporate Gear",
            "metaDescription": "Corporate Gear offers custom-embroidered corporate apparel, branded clothing, & accessories. Get YOUR logo printed on top-tier brands. Order today!",
            "metaKeywords": "Corporate Gear",
            "templateId": 0,
            "headHtml": "",
            "footerhtml": "",
            "canonicalurl": "",
            "publishDuration": null,
            "publishDate": null,
            "publishTime": null,
            "unpublishDate": null,
            "unpublishTime": null,
            "scheduleUnpublish": null,
            "redirectPageId": null,
            "createdBy": null,
            "updatedBy": null,
            "status": "P",
            "createdAt": "2022-03-12T10:16:04",
            "updatedAT": "2022-03-12T10:16:04",
            "isHomePage": "N",
            "publish_status": null,
            "menuType": "",
            "oldId": null,
            "storiesImage": null,
            "categoryId": 0,
            "displaySideBar": null,
            "description": null,
            "productSku": "[{\"name\":\"Nike Men's Team Black Therma-FIT Fleece Hoodie\",\"link\":\"https://www.corporategear.com/nike-men-team-black-therma-fit-fleece-hoodie-cn9473.html\",\"buttonText\":\"SHOP NOW\",\"image\":\"/storagemedia/temp/1/content/401/productimage/5bdae173-eeea-47e5-8b74-24d6a63f6004.jpg\"},{\"name\":\"Nike Women's Black Club Training Hoodie\",\"link\":\"https://www.corporategear.com/nike-women-black-club-training-hoodie-cj1789.html\",\"buttonText\":\"SHOP NOW\",\"image\":\"/storagemedia/temp/1/content/401/productimage/dc012bd9-0ac2-45ee-9edb-a9e7ed3a761e.jpg\"},{\"name\":\"Men's Scarlet Nike Epic Knit Jacket 2.0\",\"link\":\"https://www.corporategear.com/men-scarlet-nike-epic-knit-jacket-2-0-cn9409.html\",\"buttonText\":\"SHOP NOW\",\"image\":\"/storagemedia/temp/1/content/401/productimage/e208be32-26b3-4a4e-869c-d3b05a07acdc.jpg\"},{\"name\":\"Nike Women's Black Dri-FIT Park20 Jacket\",\"link\":\"https://www.corporategear.com/nike-women-black-dri-fit-park20-jacket-bv6899.html\",\"buttonText\":\"SHOP NOW\",\"image\":\"/storagemedia/temp/1/content/401/productimage/b9c89691-680b-4bcb-872a-fb2c616994d7.jpg\"}]",
            "isbreadcrumbShow": "false",
            "isonSitemap": false,
            "parentId": 0,
            "openGraphImagePath": null,
            "openGraphTitle": null,
            "openGraphDescription": null,
            "facebookImagePath": null,
            "facebookOpenGraphTitle": null,
            "facebookOpenGraphDescription": null,
            "twitterImagePath": null,
            "twitterOpenGraphTitle": null,
            "twitterOpenGraphDescription": null,
            "linkedinImagePath": null,
            "linkedinOpenGraphTitle": null,
            "linkedinOpenGraphDescription": null,
            "pinterestImagePath": null,
            "pinterestOpenGraphTitle": null,
            "pinterestOpenGraphDescription": null,
            "isNewStructure": false
        },
        {
            "createdName": "",
            "modifiedName": "",
            "domainName": "https://beta-cg.parsonskellogg.shop/",
            "id": 402,
            "title": "Custom Embroidered Hats with Your Company Logo",
            "pageType": "Blog",
            "passRequired": null,
            "password": "",
            "passExpiryPeriod": null,
            "tag": "",
            "author": "Super Admin",
            "previewAs": "",
            "storeId": 5,
            "slug": "custom-embroidered-hats",
            "topicTitle": "Corporate Gear",
            "metaDescription": "Corporate Gear offers custom-embroidered corporate apparel, branded clothing, & accessories. Get YOUR logo printed on top-tier brands. Order today!",
            "metaKeywords": "Corporate Gear",
            "templateId": 0,
            "headHtml": "",
            "footerhtml": "",
            "canonicalurl": "",
            "publishDuration": null,
            "publishDate": null,
            "publishTime": null,
            "unpublishDate": null,
            "unpublishTime": null,
            "scheduleUnpublish": null,
            "redirectPageId": null,
            "createdBy": null,
            "updatedBy": null,
            "status": "P",
            "createdAt": "2022-03-13T07:29:15",
            "updatedAT": "2022-03-13T07:29:15",
            "isHomePage": "N",
            "publish_status": null,
            "menuType": "",
            "oldId": null,
            "storiesImage": null,
            "categoryId": 0,
            "displaySideBar": null,
            "description": null,
            "productSku": "[{\"name\":\"Nike Swoosh Legacy Hat Black / Black\",\"link\":\"https://www.corporategear.com/nike-swoosh-legacy-hat-black-black-779797.html\",\"buttonText\":\"SHOP NOW\",\"image\":\"/storagemedia/temp/1/content/402/productimage/b2a582e1-9541-4b47-bb45-ed44d0c43180.jpg\"},{\"name\":\"Vista Grey Adidas Performance Relaxed Hat\",\"link\":\"https://www.corporategear.com/vista-grey-adidas-performance-relaxed-hat-a605.html\",\"buttonText\":\"SHOP NOW\",\"image\":\"/storagemedia/temp/1/content/402/productimage/a6675ccb-57e9-49d7-aebd-6358b02dbc0a.jpg\"},{\"name\":\"Titleist Navy / Pacific West Coast Oceanside Hat\",\"link\":\"https://www.corporategear.com/titleist-navy-pacific-west-coast-oceanside-hat-th20awco.html\",\"buttonText\":\"SHOP NOW\",\"image\":\"/storagemedia/temp/1/content/402/productimage/47b5ff30-ced6-4da9-bfb2-88b9d0ba7866.jpg\"},{\"name\":\"Grey Callaway Golf Hat\",\"link\":\"https://www.corporategear.com/grey-callaway-golf-bucket-hat-bucket.html\",\"buttonText\":\"SHOP NOW\",\"image\":\"/storagemedia/temp/1/content/402/productimage/c5bddacd-d1cc-4cd7-a877-d4446a5c8e95.jpg\"}]",
            "isbreadcrumbShow": "false",
            "isonSitemap": false,
            "parentId": 0,
            "openGraphImagePath": null,
            "openGraphTitle": null,
            "openGraphDescription": null,
            "facebookImagePath": null,
            "facebookOpenGraphTitle": null,
            "facebookOpenGraphDescription": null,
            "twitterImagePath": null,
            "twitterOpenGraphTitle": null,
            "twitterOpenGraphDescription": null,
            "linkedinImagePath": null,
            "linkedinOpenGraphTitle": null,
            "linkedinOpenGraphDescription": null,
            "pinterestImagePath": null,
            "pinterestOpenGraphTitle": null,
            "pinterestOpenGraphDescription": null,
            "isNewStructure": false
        },
        {
            "createdName": "",
            "modifiedName": "",
            "domainName": "https://beta-cg.parsonskellogg.shop/",
            "id": 403,
            "title": "Custom Jackets with Your Company Logo",
            "pageType": "Blog",
            "passRequired": null,
            "password": "",
            "passExpiryPeriod": null,
            "tag": "",
            "author": "Super Admin",
            "previewAs": "",
            "storeId": 5,
            "slug": "custom-jackets",
            "topicTitle": "Corporate Gear",
            "metaDescription": "Corporate Gear offers custom-embroidered corporate apparel, branded clothing, & accessories. Get YOUR logo printed on top-tier brands. Order today!",
            "metaKeywords": "Corporate Gear",
            "templateId": 0,
            "headHtml": "",
            "footerhtml": "",
            "canonicalurl": "",
            "publishDuration": null,
            "publishDate": null,
            "publishTime": null,
            "unpublishDate": null,
            "unpublishTime": null,
            "scheduleUnpublish": null,
            "redirectPageId": null,
            "createdBy": null,
            "updatedBy": null,
            "status": "P",
            "createdAt": "2022-03-12T10:20:25",
            "updatedAT": "2022-03-12T10:20:25",
            "isHomePage": "N",
            "publish_status": null,
            "menuType": "",
            "oldId": null,
            "storiesImage": null,
            "categoryId": 0,
            "displaySideBar": null,
            "description": null,
            "productSku": "[{\"name\":\"Men's Scarlet Nike Epic Knit Jacket 2.0\",\"link\":\"https://www.corporategear.com/men-scarlet-nike-epic-knit-jacket-2-0-cn9409.html\",\"buttonText\":\"SHOP NOW\",\"image\":\"/storagemedia/temp/1/content/403/productimage/dd2dc504-d6c1-4565-8b25-b1bc70721953.jpg\"},{\"name\":\"Nike Women's Black Epic Knit Jacket 2.0\",\"link\":\"https://www.corporategear.com/nike-women-black-epic-knit-jacket-2-0-cn9520.html\",\"buttonText\":\"SHOP NOW\",\"image\":\"/storagemedia/temp/1/content/403/productimage/480955e3-c694-418e-8fe3-fe556d0c6c53.jpg\"},{\"name\":\"Helly Hansen Men's Black Crew Hooded Jacket\",\"link\":\"https://www.corporategear.com/helly-hansen-men-black-crew-hooded-jacket-33875.html\",\"buttonText\":\"SHOP NOW\",\"image\":\"/storagemedia/temp/1/content/403/productimage/f1837d7a-d049-4c3d-88aa-0ab97fa5bde6.jpg\"},{\"name\":\"Women's Red Helly Hansen Crew Hooded Jacket\",\"link\":\"https://www.corporategear.com/women-red-helly-hansen-crew-hooded-jacket-33899.html\",\"buttonText\":\"SHOP NOW\",\"image\":\"/storagemedia/temp/1/content/403/productimage/e4d223d2-0f67-4210-8436-5627db968bbc.jpg\"}]",
            "isbreadcrumbShow": "false",
            "isonSitemap": false,
            "parentId": 0,
            "openGraphImagePath": null,
            "openGraphTitle": null,
            "openGraphDescription": null,
            "facebookImagePath": null,
            "facebookOpenGraphTitle": null,
            "facebookOpenGraphDescription": null,
            "twitterImagePath": null,
            "twitterOpenGraphTitle": null,
            "twitterOpenGraphDescription": null,
            "linkedinImagePath": null,
            "linkedinOpenGraphTitle": null,
            "linkedinOpenGraphDescription": null,
            "pinterestImagePath": null,
            "pinterestOpenGraphTitle": null,
            "pinterestOpenGraphDescription": null,
            "isNewStructure": false
        },
        {
            "createdName": "",
            "modifiedName": "",
            "domainName": "https://beta-cg.parsonskellogg.shop/",
            "id": 404,
            "title": "Custom Hats with High-Quality Embroidery",
            "pageType": "Blog",
            "passRequired": null,
            "password": "",
            "passExpiryPeriod": null,
            "tag": "",
            "author": "Super Admin",
            "previewAs": "",
            "storeId": 5,
            "slug": "custom-hats-with-highquality-embroidery",
            "topicTitle": "Corporate Gear",
            "metaDescription": "Corporate Gear offers custom-embroidered corporate apparel, branded clothing, & accessories. Get YOUR logo printed on top-tier brands. Order today!",
            "metaKeywords": "Corporate Gear",
            "templateId": 0,
            "headHtml": "",
            "footerhtml": "",
            "canonicalurl": "",
            "publishDuration": null,
            "publishDate": null,
            "publishTime": null,
            "unpublishDate": null,
            "unpublishTime": null,
            "scheduleUnpublish": null,
            "redirectPageId": null,
            "createdBy": null,
            "updatedBy": null,
            "status": "P",
            "createdAt": "2022-03-12T10:43:12",
            "updatedAT": "2022-03-12T10:43:12",
            "isHomePage": "N",
            "publish_status": null,
            "menuType": "",
            "oldId": null,
            "storiesImage": null,
            "categoryId": 0,
            "displaySideBar": null,
            "description": null,
            "productSku": "[{\"name\":\"Nike Swoosh Legacy Hat Black / Black\",\"link\":\"https://www.corporategear.com/nike-swoosh-legacy-hat-black-black-779797.html\",\"buttonText\":\"SHOP NOW\",\"image\":\"/storagemedia/temp/1/content/404/productimage/cd414ceb-b7c5-4cfb-bd19-03dcb2250af2.jpg\"},{\"name\":\"Vista Grey Adidas Performance Relaxed Hat\",\"link\":\"https://www.corporategear.com/vista-grey-adidas-performance-relaxed-hat-a605.html\",\"buttonText\":\"SHOP NOW\",\"image\":\"/storagemedia/temp/1/content/404/productimage/db3a0cd4-0adc-40ce-9583-d818337bda1c.jpg\"},{\"name\":\"Titleist Navy / Pacific West Coast Oceanside Hat\",\"link\":\"https://www.corporategear.com/titleist-navy-pacific-west-coast-oceanside-hat-th20awco.html\",\"buttonText\":\"SHOP NOW\",\"image\":\"/storagemedia/temp/1/content/404/productimage/510a88ff-f3c4-42c7-90a3-81107049810b.jpg\"},{\"name\":\"Grey Callaway Golf Hat\",\"link\":\"https://www.corporategear.com/grey-callaway-golf-bucket-hat-bucket.html\",\"buttonText\":\"SHOP NOW\",\"image\":\"/storagemedia/temp/1/content/404/productimage/d114179f-c7ad-491f-a9ea-2ff5d7558ae8.jpg\"}]",
            "isbreadcrumbShow": "false",
            "isonSitemap": false,
            "parentId": 0,
            "openGraphImagePath": null,
            "openGraphTitle": null,
            "openGraphDescription": null,
            "facebookImagePath": null,
            "facebookOpenGraphTitle": null,
            "facebookOpenGraphDescription": null,
            "twitterImagePath": null,
            "twitterOpenGraphTitle": null,
            "twitterOpenGraphDescription": null,
            "linkedinImagePath": null,
            "linkedinOpenGraphTitle": null,
            "linkedinOpenGraphDescription": null,
            "pinterestImagePath": null,
            "pinterestOpenGraphTitle": null,
            "pinterestOpenGraphDescription": null,
            "isNewStructure": false
        },
        {
            "createdName": "",
            "modifiedName": "",
            "domainName": "https://beta-cg.parsonskellogg.shop/",
            "id": 405,
            "title": "Corporate Gear is Your go-to Promotional Product Business",
            "pageType": "Blog",
            "passRequired": null,
            "password": "",
            "passExpiryPeriod": null,
            "tag": "",
            "author": "Super Admin",
            "previewAs": "",
            "storeId": 5,
            "slug": "promotional-product-business",
            "topicTitle": "Corporate Gear",
            "metaDescription": "Corporate Gear offers custom-embroidered corporate apparel, branded clothing, & accessories. Get YOUR logo printed on top-tier brands. Order today!",
            "metaKeywords": "Corporate Gear",
            "templateId": 0,
            "headHtml": "",
            "footerhtml": "",
            "canonicalurl": "",
            "publishDuration": null,
            "publishDate": null,
            "publishTime": null,
            "unpublishDate": null,
            "unpublishTime": null,
            "scheduleUnpublish": null,
            "redirectPageId": null,
            "createdBy": null,
            "updatedBy": null,
            "status": "P",
            "createdAt": "2022-03-12T10:55:34",
            "updatedAT": "2022-03-12T10:55:34",
            "isHomePage": "N",
            "publish_status": null,
            "menuType": "",
            "oldId": null,
            "storiesImage": null,
            "categoryId": 0,
            "displaySideBar": null,
            "description": null,
            "productSku": "[{\"name\":\"Men's Custom Jackets\",\"link\":\"https://www.corporategear.com/men-jackets.html?v=product-list\",\"buttonText\":\"START CUSTOMIZING\",\"image\":\"/storagemedia/temp/1/content/405/productimage/a37fc25d-acd2-45f0-8e3f-184ed012407e.jpg\"},{\"name\":\"Men's Logo Polo Shirts\",\"link\":\"https://www.corporategear.com/men-polos.html?v=product-list\",\"buttonText\":\"START CUSTOMIZING\",\"image\":\"/storagemedia/temp/1/content/405/productimage/b25db7b9-6809-453f-b664-ae38ce91e861.jpg\"},{\"name\":\"Men's Custom Quarter Zips\",\"link\":\"https://www.corporategear.com/men-quarter-zips-and-pullovers.html?v=product-list\",\"buttonText\":\"START CUSTOMIZING\",\"image\":\"/storagemedia/temp/1/content/405/productimage/362143cb-c170-4574-b114-9ef348f06eb9.jpg\"},{\"name\":\"Men's Personalized T-shirts\",\"link\":\"https://www.corporategear.com/men-t-shirt.html?v=product-list\",\"buttonText\":\"START CUSTOMIZING\",\"image\":\"/storagemedia/temp/1/content/405/productimage/0ac7c9bb-ea6a-4714-93a7-24df09b60d31.jpg\"}]",
            "isbreadcrumbShow": "false",
            "isonSitemap": false,
            "parentId": 0,
            "openGraphImagePath": null,
            "openGraphTitle": null,
            "openGraphDescription": null,
            "facebookImagePath": null,
            "facebookOpenGraphTitle": null,
            "facebookOpenGraphDescription": null,
            "twitterImagePath": null,
            "twitterOpenGraphTitle": null,
            "twitterOpenGraphDescription": null,
            "linkedinImagePath": null,
            "linkedinOpenGraphTitle": null,
            "linkedinOpenGraphDescription": null,
            "pinterestImagePath": null,
            "pinterestOpenGraphTitle": null,
            "pinterestOpenGraphDescription": null,
            "isNewStructure": false
        },
        {
            "createdName": "",
            "modifiedName": "",
            "domainName": "https://beta-cg.parsonskellogg.shop/",
            "id": 406,
            "title": "Corkcicle Personalized Tumblers are Always a Go-To for Company Drinkware",
            "pageType": "Blog",
            "passRequired": null,
            "password": "",
            "passExpiryPeriod": null,
            "tag": "",
            "author": "Super Admin",
            "previewAs": "",
            "storeId": 5,
            "slug": "personalized-tumblers",
            "topicTitle": "Corporate Gear",
            "metaDescription": "Corporate Gear offers custom-embroidered corporate apparel, branded clothing, & accessories. Get YOUR logo printed on top-tier brands. Order today!",
            "metaKeywords": "Corporate Gear",
            "templateId": 0,
            "headHtml": "",
            "footerhtml": "",
            "canonicalurl": "",
            "publishDuration": null,
            "publishDate": null,
            "publishTime": null,
            "unpublishDate": null,
            "unpublishTime": null,
            "scheduleUnpublish": null,
            "redirectPageId": null,
            "createdBy": null,
            "updatedBy": null,
            "status": "P",
            "createdAt": "2022-03-12T11:22:17",
            "updatedAT": "2022-03-12T11:22:17",
            "isHomePage": "N",
            "publish_status": null,
            "menuType": null,
            "oldId": null,
            "storiesImage": null,
            "categoryId": 0,
            "displaySideBar": null,
            "description": null,
            "productSku": null,
            "isbreadcrumbShow": null,
            "isonSitemap": false,
            "parentId": 0,
            "openGraphImagePath": null,
            "openGraphTitle": null,
            "openGraphDescription": null,
            "facebookImagePath": null,
            "facebookOpenGraphTitle": null,
            "facebookOpenGraphDescription": null,
            "twitterImagePath": null,
            "twitterOpenGraphTitle": null,
            "twitterOpenGraphDescription": null,
            "linkedinImagePath": null,
            "linkedinOpenGraphTitle": null,
            "linkedinOpenGraphDescription": null,
            "pinterestImagePath": null,
            "pinterestOpenGraphTitle": null,
            "pinterestOpenGraphDescription": null,
            "isNewStructure": false
        },
        {
            "createdName": "",
            "modifiedName": "",
            "domainName": "https://beta-cg.parsonskellogg.shop/",
            "id": 407,
            "title": "Season's Greetings From Corporate Gear",
            "pageType": "Blog",
            "passRequired": null,
            "password": "",
            "passExpiryPeriod": null,
            "tag": "",
            "author": "Super Admin",
            "previewAs": "",
            "storeId": 5,
            "slug": "seasons-greetings",
            "topicTitle": "Corporate Gear",
            "metaDescription": "Corporate Gear offers custom-embroidered corporate apparel, branded clothing, & accessories. Get YOUR logo printed on top-tier brands. Order today!",
            "metaKeywords": "Corporate Gear",
            "templateId": 0,
            "headHtml": "",
            "footerhtml": "",
            "canonicalurl": "",
            "publishDuration": null,
            "publishDate": null,
            "publishTime": null,
            "unpublishDate": null,
            "unpublishTime": null,
            "scheduleUnpublish": null,
            "redirectPageId": null,
            "createdBy": null,
            "updatedBy": null,
            "status": "P",
            "createdAt": "2022-03-13T07:31:01",
            "updatedAT": "2022-03-13T07:31:01",
            "isHomePage": "N",
            "publish_status": null,
            "menuType": "",
            "oldId": null,
            "storiesImage": null,
            "categoryId": 0,
            "displaySideBar": null,
            "description": null,
            "productSku": "[]",
            "isbreadcrumbShow": "false",
            "isonSitemap": false,
            "parentId": 0,
            "openGraphImagePath": null,
            "openGraphTitle": null,
            "openGraphDescription": null,
            "facebookImagePath": null,
            "facebookOpenGraphTitle": null,
            "facebookOpenGraphDescription": null,
            "twitterImagePath": null,
            "twitterOpenGraphTitle": null,
            "twitterOpenGraphDescription": null,
            "linkedinImagePath": null,
            "linkedinOpenGraphTitle": null,
            "linkedinOpenGraphDescription": null,
            "pinterestImagePath": null,
            "pinterestOpenGraphTitle": null,
            "pinterestOpenGraphDescription": null,
            "isNewStructure": false
        },
        {
            "createdName": "",
            "modifiedName": "",
            "domainName": "https://beta-cg.parsonskellogg.shop/",
            "id": 408,
            "title": "High-Quality Custom Embroidered Polo Shirts",
            "pageType": "Blog",
            "passRequired": null,
            "password": "",
            "passExpiryPeriod": null,
            "tag": "",
            "author": "Super Admin",
            "previewAs": "",
            "storeId": 5,
            "slug": "custom-embroidered-polo-shirts",
            "topicTitle": "Corporate Gear",
            "metaDescription": "Corporate Gear offers custom-embroidered corporate apparel, branded clothing, & accessories. Get YOUR logo printed on top-tier brands. Order today!",
            "metaKeywords": "Corporate Gear",
            "templateId": 0,
            "headHtml": "",
            "footerhtml": "",
            "canonicalurl": "",
            "publishDuration": null,
            "publishDate": null,
            "publishTime": null,
            "unpublishDate": null,
            "unpublishTime": null,
            "scheduleUnpublish": null,
            "redirectPageId": null,
            "createdBy": null,
            "updatedBy": null,
            "status": "P",
            "createdAt": "2022-03-13T08:17:38",
            "updatedAT": "2022-03-13T08:17:38",
            "isHomePage": "N",
            "publish_status": null,
            "menuType": "",
            "oldId": null,
            "storiesImage": null,
            "categoryId": 0,
            "displaySideBar": null,
            "description": null,
            "productSku": "[{\"name\":\"Peter Millar Men's Solid Performance Polo - Self Collar Navy\",\"link\":\"https://www.corporategear.com/peter-millar-men-solid-performance-polo-self-collar-navy-me0ek01s.html\",\"buttonText\":\"SHOP NOW\",\"image\":\"/storagemedia/temp/1/content/408/productimage/5e411561-21b8-40a2-8d22-c74bd325a705.jpg\"},{\"name\":\"Peter Millar Women's Black Perfect Fit Performance Polo\",\"link\":\"https://www.corporategear.com/peter-millar-women-black-perfect-fit-performance-polo-le0ek00s.html\",\"buttonText\":\"SHOP NOW\",\"image\":\"/storagemedia/temp/1/content/408/productimage/8b40326d-0732-46c8-bac8-224c7274daba.jpg\"},{\"name\":\"Footjoy Classic Stripe Polo Men's White\",\"link\":\"https://www.corporategear.com/footjoy-classic-stripe-polo-men-white-fj262.html\",\"buttonText\":\"SHOP NOW\",\"image\":\"/storagemedia/temp/1/content/408/productimage/3f3301ac-a141-433f-8b65-57d6442fb8b0.jpg\"},{\"name\":\"Lavender Footjoy End On End Open Collar Polo Women's\",\"link\":\"https://www.corporategear.com/lavender-footjoy-end-on-end-open-collar-polo-fj600-women.html\",\"buttonText\":\"SHOP NOW\",\"image\":\"/storagemedia/temp/1/content/408/productimage/1e8f2514-bbcd-4163-bfb3-d315e71e6b11.jpg\"}]",
            "isbreadcrumbShow": "false",
            "isonSitemap": false,
            "parentId": 0,
            "openGraphImagePath": null,
            "openGraphTitle": null,
            "openGraphDescription": null,
            "facebookImagePath": null,
            "facebookOpenGraphTitle": null,
            "facebookOpenGraphDescription": null,
            "twitterImagePath": null,
            "twitterOpenGraphTitle": null,
            "twitterOpenGraphDescription": null,
            "linkedinImagePath": null,
            "linkedinOpenGraphTitle": null,
            "linkedinOpenGraphDescription": null,
            "pinterestImagePath": null,
            "pinterestOpenGraphTitle": null,
            "pinterestOpenGraphDescription": null,
            "isNewStructure": false
        },
        {
            "createdName": "",
            "modifiedName": "",
            "domainName": "https://beta-cg.parsonskellogg.shop/",
            "id": 410,
            "title": "Corporate Patagonia Apparel & Gear for the Workplace",
            "pageType": "Blog",
            "passRequired": null,
            "password": "",
            "passExpiryPeriod": null,
            "tag": "",
            "author": "Super Admin",
            "previewAs": "",
            "storeId": 5,
            "slug": "corporate-patagonia",
            "topicTitle": "Corporate Gear",
            "metaDescription": "Corporate Gear offers custom-embroidered corporate apparel, branded clothing, & accessories. Get YOUR logo printed on top-tier brands. Order today!",
            "metaKeywords": "Corporate Gear",
            "templateId": 0,
            "headHtml": "",
            "footerhtml": "",
            "canonicalurl": "",
            "publishDuration": null,
            "publishDate": null,
            "publishTime": null,
            "unpublishDate": null,
            "unpublishTime": null,
            "scheduleUnpublish": null,
            "redirectPageId": null,
            "createdBy": null,
            "updatedBy": null,
            "status": "P",
            "createdAt": "2022-03-12T11:44:13",
            "updatedAT": "2022-03-12T11:44:13",
            "isHomePage": "N",
            "publish_status": null,
            "menuType": null,
            "oldId": null,
            "storiesImage": null,
            "categoryId": 0,
            "displaySideBar": null,
            "description": null,
            "productSku": null,
            "isbreadcrumbShow": null,
            "isonSitemap": false,
            "parentId": 0,
            "openGraphImagePath": null,
            "openGraphTitle": null,
            "openGraphDescription": null,
            "facebookImagePath": null,
            "facebookOpenGraphTitle": null,
            "facebookOpenGraphDescription": null,
            "twitterImagePath": null,
            "twitterOpenGraphTitle": null,
            "twitterOpenGraphDescription": null,
            "linkedinImagePath": null,
            "linkedinOpenGraphTitle": null,
            "linkedinOpenGraphDescription": null,
            "pinterestImagePath": null,
            "pinterestOpenGraphTitle": null,
            "pinterestOpenGraphDescription": null,
            "isNewStructure": false
        },
        {
            "createdName": "",
            "modifiedName": "",
            "domainName": "https://beta-cg.parsonskellogg.shop/",
            "id": 411,
            "title": "Custom Corporate Apparel & Gear for the Summer",
            "pageType": "Blog",
            "passRequired": null,
            "password": "",
            "passExpiryPeriod": null,
            "tag": "",
            "author": "Super Admin",
            "previewAs": "",
            "storeId": 5,
            "slug": "custom-corporate-apparel-for-summer",
            "topicTitle": "Corporate Gear",
            "metaDescription": "Corporate Gear offers custom-embroidered corporate apparel, branded clothing, & accessories. Get YOUR logo printed on top-tier brands. Order today!",
            "metaKeywords": "Corporate Gear",
            "templateId": 0,
            "headHtml": "",
            "footerhtml": "",
            "canonicalurl": "",
            "publishDuration": null,
            "publishDate": null,
            "publishTime": null,
            "unpublishDate": null,
            "unpublishTime": null,
            "scheduleUnpublish": null,
            "redirectPageId": null,
            "createdBy": null,
            "updatedBy": null,
            "status": "P",
            "createdAt": "2022-03-13T08:52:33",
            "updatedAT": "2022-03-13T08:52:33",
            "isHomePage": "N",
            "publish_status": null,
            "menuType": null,
            "oldId": null,
            "storiesImage": null,
            "categoryId": 0,
            "displaySideBar": null,
            "description": null,
            "productSku": null,
            "isbreadcrumbShow": null,
            "isonSitemap": false,
            "parentId": 0,
            "openGraphImagePath": null,
            "openGraphTitle": null,
            "openGraphDescription": null,
            "facebookImagePath": null,
            "facebookOpenGraphTitle": null,
            "facebookOpenGraphDescription": null,
            "twitterImagePath": null,
            "twitterOpenGraphTitle": null,
            "twitterOpenGraphDescription": null,
            "linkedinImagePath": null,
            "linkedinOpenGraphTitle": null,
            "linkedinOpenGraphDescription": null,
            "pinterestImagePath": null,
            "pinterestOpenGraphTitle": null,
            "pinterestOpenGraphDescription": null,
            "isNewStructure": false
        },
        {
            "createdName": "",
            "modifiedName": "",
            "domainName": "https://beta-cg.parsonskellogg.shop/",
            "id": 412,
            "title": "Custom Nike Clothing & Gear for Your Brand",
            "pageType": "Blog",
            "passRequired": null,
            "password": "",
            "passExpiryPeriod": null,
            "tag": "",
            "author": "Super Admin",
            "previewAs": "",
            "storeId": 5,
            "slug": "custom-nike-clothing-and-corporate-apparel",
            "topicTitle": "Corporate Gear",
            "metaDescription": "Corporate Gear offers custom-embroidered corporate apparel, branded clothing, & accessories. Get YOUR logo printed on top-tier brands. Order today!",
            "metaKeywords": "Corporate Gear",
            "templateId": 0,
            "headHtml": "",
            "footerhtml": "",
            "canonicalurl": "",
            "publishDuration": null,
            "publishDate": null,
            "publishTime": null,
            "unpublishDate": null,
            "unpublishTime": null,
            "scheduleUnpublish": null,
            "redirectPageId": null,
            "createdBy": null,
            "updatedBy": null,
            "status": "P",
            "createdAt": "2022-03-12T11:48:19",
            "updatedAT": "2022-03-12T11:48:19",
            "isHomePage": "N",
            "publish_status": null,
            "menuType": "",
            "oldId": null,
            "storiesImage": null,
            "categoryId": 0,
            "displaySideBar": null,
            "description": null,
            "productSku": "[{\"name\":\"Nike Men's Running Half-Zip Team Navy / White\",\"link\":\"https://www.corporategear.com/nike-men-running-half-zip-team-navy-white-dh4949.html\",\"buttonText\":\"SHOP NOW\",\"image\":\"/storagemedia/temp/1/content/412/productimage/572902ab-6236-440b-9104-7e619677fe19.jpg\"},{\"name\":\"Team Purple / White Nike Epic Knit Jacket 2.0 Women's\",\"link\":\"https://www.corporategear.com/team-purple-white-nike-epic-knit-jacket-2-0-cn9520-women.html\",\"buttonText\":\"SHOP NOW\",\"image\":\"/storagemedia/temp/1/content/412/productimage/a57b1427-33d2-4cf1-baf8-1d19f456bf9e.jpg\"},{\"name\":\"Nike Men's Team Black Therma-FIT Fleece Hoodie\",\"link\":\"https://www.corporategear.com/nike-men-team-black-therma-fit-fleece-hoodie-cn9473.html\",\"buttonText\":\"SHOP NOW\",\"image\":\"/storagemedia/temp/1/content/412/productimage/3f02bbbe-b9cc-4a68-86fd-38d0ba290794.jpg\"},{\"name\":\"Nike Men's Black Legend Long-Sleeve T-Shirt\",\"link\":\"https://www.corporategear.com/nike-men-black-legend-long-sleeve-t-shirt-727980.html\",\"buttonText\":\"SHOP NOW\",\"image\":\"/storagemedia/temp/1/content/412/productimage/e7de0ead-a385-4fad-a844-d06cf71e06d1.jpg\"}]",
            "isbreadcrumbShow": "false",
            "isonSitemap": false,
            "parentId": 0,
            "openGraphImagePath": null,
            "openGraphTitle": null,
            "openGraphDescription": null,
            "facebookImagePath": null,
            "facebookOpenGraphTitle": null,
            "facebookOpenGraphDescription": null,
            "twitterImagePath": null,
            "twitterOpenGraphTitle": null,
            "twitterOpenGraphDescription": null,
            "linkedinImagePath": null,
            "linkedinOpenGraphTitle": null,
            "linkedinOpenGraphDescription": null,
            "pinterestImagePath": null,
            "pinterestOpenGraphTitle": null,
            "pinterestOpenGraphDescription": null,
            "isNewStructure": false
        },
        {
            "createdName": "",
            "modifiedName": "",
            "domainName": "https://beta-cg.parsonskellogg.shop/",
            "id": 413,
            "title": "Logo Golf Shirts for Your Corporate Portfolio",
            "pageType": "Blog",
            "passRequired": null,
            "password": "",
            "passExpiryPeriod": null,
            "tag": "",
            "author": "Super Admin",
            "previewAs": "",
            "storeId": 5,
            "slug": "logo-golf-shirts",
            "topicTitle": "Corporate Gear",
            "metaDescription": "Corporate Gear offers custom-embroidered corporate apparel, branded clothing, & accessories. Get YOUR logo printed on top-tier brands. Order today!",
            "metaKeywords": "Corporate Gear",
            "templateId": 0,
            "headHtml": "",
            "footerhtml": "",
            "canonicalurl": "",
            "publishDuration": null,
            "publishDate": null,
            "publishTime": null,
            "unpublishDate": null,
            "unpublishTime": null,
            "scheduleUnpublish": null,
            "redirectPageId": null,
            "createdBy": null,
            "updatedBy": null,
            "status": "P",
            "createdAt": "2022-03-13T09:00:50",
            "updatedAT": "2022-03-13T09:00:50",
            "isHomePage": "N",
            "publish_status": null,
            "menuType": "",
            "oldId": null,
            "storiesImage": null,
            "categoryId": 0,
            "displaySideBar": null,
            "description": null,
            "productSku": "[{\"name\":\"Women's Team Orange Nike Dri-FIT Franchise Polo\",\"link\":\"https://www.corporategear.com/women-team-orange-nike-dri-fit-franchise-polo-cu3206.html\",\"buttonText\":\"SHOP NOW\",\"image\":\"/storagemedia/temp/1/content/413/productimage/4f736a5f-67b2-4f3d-b0dd-859b2439f222.jpg\"},{\"name\":\"Collegiate Green Adidas Performance Polo Men's\",\"link\":\"corporategear.com/collegiate-green-adidas-performance-polo-men-a230.html\",\"buttonText\":\"SHOP NOW\",\"image\":\"/storagemedia/temp/1/content/413/productimage/1e322c1b-4d57-44bd-a3fd-a0bd9d27e421.jpg\"},{\"name\":\"Footjoy Prodry Performance Stretch Pique Polo Men's White\",\"link\":\"https://www.corporategear.com/footjoy-prodry-performance-stretch-pique-polo-men-white-fj502.html\",\"buttonText\":\"SHOP NOW\",\"image\":\"/storagemedia/temp/1/content/413/productimage/b84a79b2-d0cd-4692-b0ab-1e2268931cd1.jpg\"},{\"name\":\"Callaway Magnetic Blue Men's Golf Birdseye Polo\",\"link\":\"https://www.corporategear.com/callaway-magnetic-blue-men-golf-birdseye-polo-cgm692.html\",\"buttonText\":\"SHOP NOW\",\"image\":\"/storagemedia/temp/1/content/413/productimage/dcea4131-d880-4228-9f01-f9505bafec63.jpg\"}]",
            "isbreadcrumbShow": "false",
            "isonSitemap": false,
            "parentId": 0,
            "openGraphImagePath": null,
            "openGraphTitle": null,
            "openGraphDescription": null,
            "facebookImagePath": null,
            "facebookOpenGraphTitle": null,
            "facebookOpenGraphDescription": null,
            "twitterImagePath": null,
            "twitterOpenGraphTitle": null,
            "twitterOpenGraphDescription": null,
            "linkedinImagePath": null,
            "linkedinOpenGraphTitle": null,
            "linkedinOpenGraphDescription": null,
            "pinterestImagePath": null,
            "pinterestOpenGraphTitle": null,
            "pinterestOpenGraphDescription": null,
            "isNewStructure": false
        },
        {
            "createdName": "",
            "modifiedName": "",
            "domainName": "https://beta-cg.parsonskellogg.shop/",
            "id": 414,
            "title": "Peter Millar Custom Golf Apparel",
            "pageType": "Blog",
            "passRequired": null,
            "password": "",
            "passExpiryPeriod": null,
            "tag": "Article, Brand Story",
            "author": "Super Admin",
            "previewAs": "",
            "storeId": 5,
            "slug": "custom-golf-apparel",
            "topicTitle": "Peter Millar Custom Golf Apparel – Corporate Gear",
            "metaDescription": "Peter Millar custom golf apparel is ready for the office or green, delivering professional looks with an edge.",
            "metaKeywords": "custom golf apparel, custom golf shirts, custom golf polos, embroidered golf shirts, custom golf shirt, logo golf shirts",
            "templateId": 0,
            "headHtml": "",
            "footerhtml": "",
            "canonicalurl": "",
            "publishDuration": null,
            "publishDate": null,
            "publishTime": null,
            "unpublishDate": null,
            "unpublishTime": null,
            "scheduleUnpublish": null,
            "redirectPageId": null,
            "createdBy": null,
            "updatedBy": null,
            "status": "P",
            "createdAt": "2022-03-12T11:59:30",
            "updatedAT": "2022-03-12T11:59:30",
            "isHomePage": "N",
            "publish_status": null,
            "menuType": "",
            "oldId": null,
            "storiesImage": null,
            "categoryId": 0,
            "displaySideBar": null,
            "description": null,
            "productSku": "[{\"name\":\"Peter Millar Men's Black Solid Performance Polo - Self Collar\",\"link\":\"https://www.corporategear.com/peter-millar-men-black-solid-performance-polo-self-collar-me0ek01s.html\",\"buttonText\":\"DETAILS\",\"image\":\"/storagemedia/temp/1/content/414/productimage/a421a7a4-11e4-4e17-b5b9-8cfa077f7575.jpeg\"},{\"name\":\"Peter Millar Women's Black Button Polo\",\"link\":\"https://www.corporategear.com/peter-millar-women-black-button-polo-le0ek10s.html\",\"buttonText\":\"DETAILS\",\"image\":\"/storagemedia/temp/1/content/414/productimage/7fc39efa-f5a0-46be-ac18-15fe13b953f4.jpeg\"},{\"name\":\"Peter Millar Men's Balsam Autumn Crest Quarter-Zip\",\"link\":\"https://www.corporategear.com/balsam-peter-millar-autumn-crest-quarter-zip-men-me0s01.html\",\"buttonText\":\"DETAILS\",\"image\":\"/storagemedia/temp/1/content/414/productimage/23a92b8b-a2ba-42d6-94e3-02432aa696ee.jpeg\"},{\"name\":\"Peter Millar Women's Black Raglan Sleeve Perth Layer Quarter-Zip\",\"link\":\"https://www.corporategear.com/peter-millar-women-black-raglan-sleeve-perth-layer-quarter-zip-le0ek43.html\",\"buttonText\":\"DETAILS\",\"image\":\"/storagemedia/temp/1/content/414/productimage/75a8a0dd-2b18-485f-a7b2-17eaf60d3709.jpg\"}]",
            "isbreadcrumbShow": "false",
            "isonSitemap": false,
            "parentId": 0,
            "openGraphImagePath": null,
            "openGraphTitle": null,
            "openGraphDescription": null,
            "facebookImagePath": null,
            "facebookOpenGraphTitle": null,
            "facebookOpenGraphDescription": null,
            "twitterImagePath": null,
            "twitterOpenGraphTitle": null,
            "twitterOpenGraphDescription": null,
            "linkedinImagePath": null,
            "linkedinOpenGraphTitle": null,
            "linkedinOpenGraphDescription": null,
            "pinterestImagePath": null,
            "pinterestOpenGraphTitle": null,
            "pinterestOpenGraphDescription": null,
            "isNewStructure": false
        },
        {
            "createdName": "",
            "modifiedName": "",
            "domainName": "https://beta-cg.parsonskellogg.shop/",
            "id": 415,
            "title": "Eco Friendly Promotional Products that Put Your Brand in the Spotlight",
            "pageType": "Blog",
            "passRequired": null,
            "password": "",
            "passExpiryPeriod": null,
            "tag": "",
            "author": "Super Admin",
            "previewAs": "",
            "storeId": 5,
            "slug": "eco-friendly-promotional-products",
            "topicTitle": "Corporate Gear",
            "metaDescription": "Corporate Gear offers custom-embroidered corporate apparel, branded clothing, & accessories. Get YOUR logo printed on top-tier brands. Order today!",
            "metaKeywords": "Corporate Gear",
            "templateId": 0,
            "headHtml": "",
            "footerhtml": "",
            "canonicalurl": "",
            "publishDuration": null,
            "publishDate": null,
            "publishTime": null,
            "unpublishDate": null,
            "unpublishTime": null,
            "scheduleUnpublish": null,
            "redirectPageId": null,
            "createdBy": null,
            "updatedBy": null,
            "status": "P",
            "createdAt": "2022-03-13T09:08:50",
            "updatedAT": "2022-03-13T09:08:50",
            "isHomePage": "N",
            "publish_status": null,
            "menuType": "",
            "oldId": null,
            "storiesImage": null,
            "categoryId": 0,
            "displaySideBar": null,
            "description": null,
            "productSku": "[{\"name\":\"Corporate Patagonia\",\"link\":\"https://www.corporategear.com/patagonia.html?v=brand-product-list\",\"buttonText\":\"SHOP NOW\",\"image\":\"/storagemedia/temp/1/content/415/productimage/82f194b8-3fa8-4cb0-a4d4-1fd191fba08c.png\"},{\"name\":\"The North Face Apparel\",\"link\":\"https://www.corporategear.com/the-north-face.html?v=brand-product-list\",\"buttonText\":\"SHOP NOW\",\"image\":\"/storagemedia/temp/1/content/415/productimage/def7f636-ca50-499e-b331-784e5ec3ddaa.png\"},{\"name\":\"Custom YETI Cups\",\"link\":\"https://www.corporategear.com/yeti.html?v=brand-product-list\",\"buttonText\":\"SHOP NOW\",\"image\":\"/storagemedia/temp/1/content/415/productimage/b6be7348-4c4b-4606-bcf3-c4b39f297c7d.png\"},{\"name\":\"S'well Custom Drinkware\",\"link\":\"https://www.corporategear.com/swell.html?v=brand-product-list\",\"buttonText\":\"SHOP NOW\",\"image\":\"/storagemedia/temp/1/content/415/productimage/884c1a8b-9468-48d3-8435-38da92cb90db.png\"}]",
            "isbreadcrumbShow": "false",
            "isonSitemap": false,
            "parentId": 0,
            "openGraphImagePath": null,
            "openGraphTitle": null,
            "openGraphDescription": null,
            "facebookImagePath": null,
            "facebookOpenGraphTitle": null,
            "facebookOpenGraphDescription": null,
            "twitterImagePath": null,
            "twitterOpenGraphTitle": null,
            "twitterOpenGraphDescription": null,
            "linkedinImagePath": null,
            "linkedinOpenGraphTitle": null,
            "linkedinOpenGraphDescription": null,
            "pinterestImagePath": null,
            "pinterestOpenGraphTitle": null,
            "pinterestOpenGraphDescription": null,
            "isNewStructure": false
        },
        {
            "createdName": "",
            "modifiedName": "",
            "domainName": "https://beta-cg.parsonskellogg.shop/",
            "id": 416,
            "title": "Social Media Marketing Tips that Help Your Brand Succeed",
            "pageType": "Blog",
            "passRequired": null,
            "password": "",
            "passExpiryPeriod": null,
            "tag": "",
            "author": "Super Admin",
            "previewAs": "",
            "storeId": 5,
            "slug": "social-media-marketing-tips",
            "topicTitle": "Corporate Gear",
            "metaDescription": "Corporate Gear offers custom-embroidered corporate apparel, branded clothing, & accessories. Get YOUR logo printed on top-tier brands. Order today!",
            "metaKeywords": "Corporate Gear",
            "templateId": 0,
            "headHtml": "",
            "footerhtml": "",
            "canonicalurl": "",
            "publishDuration": null,
            "publishDate": null,
            "publishTime": null,
            "unpublishDate": null,
            "unpublishTime": null,
            "scheduleUnpublish": null,
            "redirectPageId": null,
            "createdBy": null,
            "updatedBy": null,
            "status": "P",
            "createdAt": "2022-03-13T09:16:53",
            "updatedAT": "2022-03-13T09:16:53",
            "isHomePage": "N",
            "publish_status": null,
            "menuType": "",
            "oldId": null,
            "storiesImage": null,
            "categoryId": 0,
            "displaySideBar": null,
            "description": null,
            "productSku": "[{\"name\":\"Nike Men's Team Black Therma-FIT Fleece Hoodie\",\"link\":\"https://www.corporategear.com/nike-men-team-black-therma-fit-fleece-hoodie-cn9473.html\",\"buttonText\":\"SHOP NOW\",\"image\":\"/storagemedia/temp/1/content/416/productimage/6040a319-8d99-4c07-b1ba-73077093e09f.jpg\"},{\"name\":\"Adidas Women's Black Creator T-Shirt\",\"link\":\"https://www.corporategear.com/adidas-women-black-creator-t-shirt-12h5.html\",\"buttonText\":\"SHOP NOW\",\"image\":\"/storagemedia/temp/1/content/416/productimage/d1ea82be-0756-4a91-b5d2-2b3d4f19204c.jpg\"},{\"name\":\"Order Under Armour ozsee Sackpack Royal\",\"link\":\"https://www.corporategear.com/under-armour-ozsee-sackpack-1240539-royal.html\",\"buttonText\":\"SHOP NOW\",\"image\":\"/storagemedia/temp/1/content/416/productimage/9f122b52-2b8f-4a99-bc40-31966303263d.jpg\"},{\"name\":\"White YETI  Rambler Bottle 18 oz Chug\",\"link\":\"https://www.corporategear.com/white-yeti-yramb18c-rambler-bottle-18-oz-chug.html\",\"buttonText\":\"SHOP NOW\",\"image\":\"/storagemedia/temp/1/content/416/productimage/1fc27353-c3fb-4c74-8308-849606a4754c.jpg\"}]",
            "isbreadcrumbShow": "false",
            "isonSitemap": false,
            "parentId": 0,
            "openGraphImagePath": null,
            "openGraphTitle": null,
            "openGraphDescription": null,
            "facebookImagePath": null,
            "facebookOpenGraphTitle": null,
            "facebookOpenGraphDescription": null,
            "twitterImagePath": null,
            "twitterOpenGraphTitle": null,
            "twitterOpenGraphDescription": null,
            "linkedinImagePath": null,
            "linkedinOpenGraphTitle": null,
            "linkedinOpenGraphDescription": null,
            "pinterestImagePath": null,
            "pinterestOpenGraphTitle": null,
            "pinterestOpenGraphDescription": null,
            "isNewStructure": false
        },
        {
            "createdName": "",
            "modifiedName": "",
            "domainName": "https://beta-cg.parsonskellogg.shop/",
            "id": 417,
            "title": "Corporate Holiday Gifts Popular in 2021",
            "pageType": "Blog",
            "passRequired": null,
            "password": "",
            "passExpiryPeriod": null,
            "tag": "",
            "author": "Super Admin",
            "previewAs": "",
            "storeId": 5,
            "slug": "corporate-holiday-gifts",
            "topicTitle": "Corporate Gear",
            "metaDescription": "Corporate Gear offers custom-embroidered corporate apparel, branded clothing, & accessories. Get YOUR logo printed on top-tier brands. Order today!",
            "metaKeywords": "Corporate Gear",
            "templateId": 0,
            "headHtml": "",
            "footerhtml": "",
            "canonicalurl": "",
            "publishDuration": null,
            "publishDate": null,
            "publishTime": null,
            "unpublishDate": null,
            "unpublishTime": null,
            "scheduleUnpublish": null,
            "redirectPageId": null,
            "createdBy": null,
            "updatedBy": null,
            "status": "P",
            "createdAt": "2022-03-12T12:10:35",
            "updatedAT": "2022-03-12T12:10:35",
            "isHomePage": "N",
            "publish_status": null,
            "menuType": "",
            "oldId": null,
            "storiesImage": null,
            "categoryId": 0,
            "displaySideBar": null,
            "description": null,
            "productSku": "[{\"name\":\"Men's Custom Clothing\",\"link\":\"https://www.corporategear.com/men.html?v=product-list\",\"buttonText\":\"\",\"image\":\"/storagemedia/temp/1/content/417/productimage/fece6cea-a3a9-431e-a77d-b792fe7288d9.jpg\"},{\"name\":\"Women's Custom Apparel\",\"link\":\"https://www.corporategear.com/women.html?v=product-list\",\"buttonText\":\"\",\"image\":\"/storagemedia/temp/1/content/417/productimage/abcaeaef-d638-4631-be59-f25fec0b90a1.jpg\"},{\"name\":\"Custom Drinkware & Gifts\",\"link\":\"https://www.corporategear.com/accessories-drinkware.html?v=product-list\",\"buttonText\":\"\",\"image\":\"/storagemedia/temp/1/content/417/productimage/6f60d290-8e19-46a8-b659-be93a0a13e1c.jpg\"},{\"name\":\"Personalized Office Gifts\",\"link\":\"https://www.corporategear.com/accessories-office.html?v=product-list\",\"buttonText\":\"\",\"image\":\"/storagemedia/temp/1/content/417/productimage/687c9796-8f57-4f1a-a379-46f4bd4ae0a8.jpg\"}]",
            "isbreadcrumbShow": "false",
            "isonSitemap": false,
            "parentId": 0,
            "openGraphImagePath": null,
            "openGraphTitle": null,
            "openGraphDescription": null,
            "facebookImagePath": null,
            "facebookOpenGraphTitle": null,
            "facebookOpenGraphDescription": null,
            "twitterImagePath": null,
            "twitterOpenGraphTitle": null,
            "twitterOpenGraphDescription": null,
            "linkedinImagePath": null,
            "linkedinOpenGraphTitle": null,
            "linkedinOpenGraphDescription": null,
            "pinterestImagePath": null,
            "pinterestOpenGraphTitle": null,
            "pinterestOpenGraphDescription": null,
            "isNewStructure": false
        },
        {
            "createdName": "",
            "modifiedName": "",
            "domainName": "https://beta-cg.parsonskellogg.shop/",
            "id": 418,
            "title": "Custom Patagonia will No Longer Have Logos",
            "pageType": "Blog",
            "passRequired": null,
            "password": "",
            "passExpiryPeriod": null,
            "tag": "",
            "author": "Super Admin",
            "previewAs": "",
            "storeId": 5,
            "slug": "custom-patagonia-will-no-longer-have-logos",
            "topicTitle": "Custom Patagonia will No Longer Have Logos - Corporate Gear",
            "metaDescription": "Custom Patagonia will no longer have logos, and we&#39;re okay with that. Learn more about sustainable company clothing and Patagonia gifts.",
            "metaKeywords": "patagonia, custom patagonia, company clothing, branded patagonia, patagonia gifts",
            "templateId": 0,
            "headHtml": "",
            "footerhtml": "",
            "canonicalurl": "",
            "publishDuration": null,
            "publishDate": null,
            "publishTime": null,
            "unpublishDate": null,
            "unpublishTime": null,
            "scheduleUnpublish": null,
            "redirectPageId": null,
            "createdBy": null,
            "updatedBy": null,
            "status": "P",
            "createdAt": "2022-03-13T09:20:35",
            "updatedAT": "2022-03-13T09:20:35",
            "isHomePage": "N",
            "publish_status": null,
            "menuType": "",
            "oldId": null,
            "storiesImage": null,
            "categoryId": 0,
            "displaySideBar": null,
            "description": null,
            "productSku": "[{\"name\":\"Patagonia Capilene Cool Trail Shirt Forge Grey Men's\",\"link\":\"https://www.corporategear.com/patagonia-capilene-cool-trail-shirt-forge-grey-men-24496.html\",\"buttonText\":\"SHOP NOW\",\"image\":\"/storagemedia/temp/1/content/418/productimage/38f694c0-284c-4902-aeff-26710b9a4a02.jpg\"},{\"name\":\"Patagonia Women's Ahnya Quarter-Zip Smolder Blue\",\"link\":\"https://www.corporategear.com/patagonia-women-ahnya-quarter-zip-smolder-blue-42150.html\",\"buttonText\":\"SHOP NOW\",\"image\":\"/storagemedia/temp/1/content/418/productimage/cd987b7f-831a-4935-82f1-65fff24302e6.jpg\"},{\"name\":\"Patagonia Refugio Daypack Backpack 30L Black\",\"link\":\"https://www.corporategear.com/patagonia-refugio-daypack-backpack-30l-black-47928.html\",\"buttonText\":\"SHOP NOW\",\"image\":\"/storagemedia/temp/1/content/418/productimage/b3676924-a365-41ce-afc3-34e4694fff32.jpg\"},{\"name\":\"Patagonia Black Hole Duffel Bag 55L Black\",\"link\":\"https://www.corporategear.com/patagonia-black-hole-duffel-bag-55l-black-49342.html\",\"buttonText\":\"SHOP NOW\",\"image\":\"/storagemedia/temp/1/content/418/productimage/2b07766f-a82a-475a-9f2c-178983c2aa39.jpg\"}]",
            "isbreadcrumbShow": "false",
            "isonSitemap": false,
            "parentId": 0,
            "openGraphImagePath": null,
            "openGraphTitle": null,
            "openGraphDescription": null,
            "facebookImagePath": null,
            "facebookOpenGraphTitle": null,
            "facebookOpenGraphDescription": null,
            "twitterImagePath": null,
            "twitterOpenGraphTitle": null,
            "twitterOpenGraphDescription": null,
            "linkedinImagePath": null,
            "linkedinOpenGraphTitle": null,
            "linkedinOpenGraphDescription": null,
            "pinterestImagePath": null,
            "pinterestOpenGraphTitle": null,
            "pinterestOpenGraphDescription": null,
            "isNewStructure": false
        }
    ]
}