[
    {
        "id": 1,
        "srno": 1,
        "month": "Apr",
        "total_orders": 21,
        "subtotal": 16682,
        "tax": 1578.52,
        "shipping": 7.44,
        "refund": 280.81,
        "discount": 85.26,
        "adj_amount": 100.92,
        "total": 18002.81
    },
    {
        "id": 2,
        "srno": 2,
        "month": "Apr",
        "total_orders": 22,
        "subtotal": 37983,
        "tax": 1246.36,
        "shipping": 9.18,
        "refund": 470.39,
        "discount": 272.23,
        "adj_amount": 150.48,
        "total": 38646.4
    },
    {
        "id": 3,
        "srno": 3,
        "month": "Feb",
        "total_orders": 27,
        "subtotal": 56412,
        "tax": 2119.11,
        "shipping": 32.67,
        "refund": 113.08,
        "discount": 113.94,
        "adj_amount": 171.04,
        "total": 58507.8
    },
    {
        "id": 4,
        "srno": 4,
        "month": "Feb",
        "total_orders": 44,
        "subtotal": 70854,
        "tax": 5265.75,
        "shipping": 45.47,
        "refund": 432.2,
        "discount": 102.07,
        "adj_amount": 196.57,
        "total": 75827.52
    },
    {
        "id": 5,
        "srno": 5,
        "month": "Jun",
        "total_orders": 16,
        "subtotal": 76251,
        "tax": 3494.95,
        "shipping": 19.44,
        "refund": 496.65,
        "discount": 188.95,
        "adj_amount": 55.74,
        "total": 79135.53
    },
    {
        "id": 6,
        "srno": 6,
        "month": "Jan",
        "total_orders": 13,
        "subtotal": 50748,
        "tax": 1236.21,
        "shipping": 10.3,
        "refund": 340.76,
        "discount": 265.11,
        "adj_amount": 48.18,
        "total": 51436.82
    },
    {
        "id": 7,
        "srno": 7,
        "month": "Apr",
        "total_orders": 24,
        "subtotal": 96151,
        "tax": 3883.64,
        "shipping": 37.76,
        "refund": 308.33,
        "discount": 260.75,
        "adj_amount": 186.72,
        "total": 99690.04
    },
    {
        "id": 8,
        "srno": 8,
        "month": "Jun",
        "total_orders": 18,
        "subtotal": 89786,
        "tax": 6406.98,
        "shipping": 39.44,
        "refund": 278.08,
        "discount": 192.31,
        "adj_amount": 139.45,
        "total": 95901.48
    },
    {
        "id": 9,
        "srno": 9,
        "month": "Apr",
        "total_orders": 46,
        "subtotal": 69022,
        "tax": 5854.96,
        "shipping": 19.33,
        "refund": 69.15,
        "discount": 69.9,
        "adj_amount": 178.4,
        "total": 74935.64
    },
    {
        "id": 10,
        "srno": 10,
        "month": "Jan",
        "total_orders": 19,
        "subtotal": 35739,
        "tax": 2171.56,
        "shipping": 21.3,
        "refund": 180.1,
        "discount": 203.29,
        "adj_amount": 14.39,
        "total": 37562.86
    },
    {
        "id": 11,
        "srno": 11,
        "month": "Aug",
        "total_orders": 12,
        "subtotal": 83471,
        "tax": 6450.32,
        "shipping": 20.26,
        "refund": 236.05,
        "discount": 297.5,
        "adj_amount": 131.43,
        "total": 89539.46
    },
    {
        "id": 12,
        "srno": 12,
        "month": "Sep",
        "total_orders": 30,
        "subtotal": 55191,
        "tax": 2940.82,
        "shipping": 36.47,
        "refund": 452.42,
        "discount": 252.39,
        "adj_amount": 109.74,
        "total": 57573.22
    },
    {
        "id": 13,
        "srno": 13,
        "month": "May",
        "total_orders": 39,
        "subtotal": 67894,
        "tax": 3886.64,
        "shipping": 5.96,
        "refund": 463.32,
        "discount": 54.37,
        "adj_amount": 29.92,
        "total": 71298.83
    },
    {
        "id": 14,
        "srno": 14,
        "month": "Mar",
        "total_orders": 47,
        "subtotal": 32365,
        "tax": 2685.67,
        "shipping": 41.82,
        "refund": 32.68,
        "discount": 75.31,
        "adj_amount": 180.76,
        "total": 35165.26
    },
    {
        "id": 15,
        "srno": 15,
        "month": "Oct",
        "total_orders": 17,
        "subtotal": 27116,
        "tax": 1550.58,
        "shipping": 42.64,
        "refund": 4.98,
        "discount": 37.37,
        "adj_amount": 112.12,
        "total": 28778.99
    },
    {
        "id": 16,
        "srno": 16,
        "month": "Aug",
        "total_orders": 11,
        "subtotal": 11045,
        "tax": 880.63,
        "shipping": 8.53,
        "refund": 480.96,
        "discount": 148.62,
        "adj_amount": 67.29,
        "total": 11371.87
    },
    {
        "id": 17,
        "srno": 17,
        "month": "Nov",
        "total_orders": 13,
        "subtotal": 55543,
        "tax": 2852.52,
        "shipping": 44.34,
        "refund": 295.18,
        "discount": 143.56,
        "adj_amount": 34.17,
        "total": 58035.29
    },
    {
        "id": 18,
        "srno": 18,
        "month": "Feb",
        "total_orders": 31,
        "subtotal": 21343,
        "tax": 1911.6,
        "shipping": 11.44,
        "refund": 111.91,
        "discount": 237.29,
        "adj_amount": 83.15,
        "total": 22999.99
    },
    {
        "id": 19,
        "srno": 19,
        "month": "Jan",
        "total_orders": 32,
        "subtotal": 48858,
        "tax": 1016.47,
        "shipping": 4.38,
        "refund": 388.22,
        "discount": 194.79,
        "adj_amount": 64.43,
        "total": 49360.27
    },
    {
        "id": 20,
        "srno": 20,
        "month": "May",
        "total_orders": 13,
        "subtotal": 68037,
        "tax": 1487.17,
        "shipping": 47.94,
        "refund": 241.74,
        "discount": 279.28,
        "adj_amount": 68.08,
        "total": 69119.17
    },
    {
        "id": 21,
        "srno": 21,
        "month": "Jan",
        "total_orders": 31,
        "subtotal": 41306,
        "tax": 3252.66,
        "shipping": 18.2,
        "refund": 369.43,
        "discount": 13.25,
        "adj_amount": 84.81,
        "total": 44278.99
    },
    {
        "id": 22,
        "srno": 22,
        "month": "Feb",
        "total_orders": 36,
        "subtotal": 34924,
        "tax": 2363.09,
        "shipping": 41.45,
        "refund": 139.18,
        "discount": 53.74,
        "adj_amount": 30.42,
        "total": 37166.04
    },
    {
        "id": 23,
        "srno": 23,
        "month": "Aug",
        "total_orders": 28,
        "subtotal": 29171,
        "tax": 1119.3,
        "shipping": 38.41,
        "refund": 156.06,
        "discount": 198.51,
        "adj_amount": 62.06,
        "total": 30036.2
    },
    {
        "id": 24,
        "srno": 24,
        "month": "May",
        "total_orders": 29,
        "subtotal": 59074,
        "tax": 2653.68,
        "shipping": 41.28,
        "refund": 489.46,
        "discount": 286.41,
        "adj_amount": 152.57,
        "total": 61145.66
    },
    {
        "id": 25,
        "srno": 25,
        "month": "Jun",
        "total_orders": 16,
        "subtotal": 79778,
        "tax": 2007.7,
        "shipping": 40.78,
        "refund": 212.77,
        "discount": 160.25,
        "adj_amount": 132.75,
        "total": 81586.21
    },
    {
        "id": 26,
        "srno": 26,
        "month": "Mar",
        "total_orders": 39,
        "subtotal": 60726,
        "tax": 5019.34,
        "shipping": 11.7,
        "refund": 218.88,
        "discount": 160.2,
        "adj_amount": 30.14,
        "total": 65408.1
    },
    {
        "id": 27,
        "srno": 27,
        "month": "Oct",
        "total_orders": 13,
        "subtotal": 71181,
        "tax": 4312.53,
        "shipping": 35.53,
        "refund": 199.66,
        "discount": 18.59,
        "adj_amount": 97.23,
        "total": 75408.04
    },
    {
        "id": 28,
        "srno": 28,
        "month": "Dec",
        "total_orders": 24,
        "subtotal": 73981,
        "tax": 5269.37,
        "shipping": 41.16,
        "refund": 363.52,
        "discount": 247.48,
        "adj_amount": 108.36,
        "total": 78788.89
    },
    {
        "id": 29,
        "srno": 29,
        "month": "Jun",
        "total_orders": 23,
        "subtotal": 40638,
        "tax": 3460.25,
        "shipping": 16.2,
        "refund": 462.52,
        "discount": 226.16,
        "adj_amount": 132.92,
        "total": 43558.69
    },
    {
        "id": 30,
        "srno": 30,
        "month": "Apr",
        "total_orders": 28,
        "subtotal": 92508,
        "tax": 8117.13,
        "shipping": 11.86,
        "refund": 397.66,
        "discount": 246.22,
        "adj_amount": 54.69,
        "total": 100047.8
    },
    {
        "id": 31,
        "srno": 31,
        "month": "Dec",
        "total_orders": 44,
        "subtotal": 67945,
        "tax": 3996.79,
        "shipping": 47.4,
        "refund": 397.94,
        "discount": 212.68,
        "adj_amount": 83.23,
        "total": 71461.8
    },
    {
        "id": 32,
        "srno": 32,
        "month": "May",
        "total_orders": 12,
        "subtotal": 69133,
        "tax": 5583.83,
        "shipping": 3.68,
        "refund": 467.57,
        "discount": 252.57,
        "adj_amount": 3.74,
        "total": 74004.11
    },
    {
        "id": 33,
        "srno": 33,
        "month": "Jun",
        "total_orders": 29,
        "subtotal": 81689,
        "tax": 8113.0,
        "shipping": 5.45,
        "refund": 40.85,
        "discount": 48.26,
        "adj_amount": 79.15,
        "total": 89797.49
    },
    {
        "id": 34,
        "srno": 34,
        "month": "Mar",
        "total_orders": 49,
        "subtotal": 56824,
        "tax": 2199.07,
        "shipping": 39.0,
        "refund": 426.9,
        "discount": 272.28,
        "adj_amount": 153.19,
        "total": 58516.08
    },
    {
        "id": 35,
        "srno": 35,
        "month": "Jan",
        "total_orders": 12,
        "subtotal": 35838,
        "tax": 3327.8,
        "shipping": 24.51,
        "refund": 371.79,
        "discount": 223.06,
        "adj_amount": 17.34,
        "total": 38612.8
    },
    {
        "id": 36,
        "srno": 36,
        "month": "Jul",
        "total_orders": 20,
        "subtotal": 68569,
        "tax": 5305.7,
        "shipping": 4.6,
        "refund": 73.12,
        "discount": 259.62,
        "adj_amount": 107.01,
        "total": 73653.57
    },
    {
        "id": 37,
        "srno": 37,
        "month": "Jan",
        "total_orders": 16,
        "subtotal": 52877,
        "tax": 2076.88,
        "shipping": 13.58,
        "refund": 230.08,
        "discount": 250.29,
        "adj_amount": 111.52,
        "total": 54598.61
    },
    {
        "id": 38,
        "srno": 38,
        "month": "Aug",
        "total_orders": 31,
        "subtotal": 43744,
        "tax": 4257.15,
        "shipping": 21.83,
        "refund": 437.51,
        "discount": 46.83,
        "adj_amount": 45.96,
        "total": 47584.6
    },
    {
        "id": 39,
        "srno": 39,
        "month": "Mar",
        "total_orders": 13,
        "subtotal": 35926,
        "tax": 1022.2,
        "shipping": 22.11,
        "refund": 398.56,
        "discount": 168.56,
        "adj_amount": 128.05,
        "total": 36531.24
    },
    {
        "id": 40,
        "srno": 40,
        "month": "Dec",
        "total_orders": 16,
        "subtotal": 78812,
        "tax": 2886.65,
        "shipping": 36.77,
        "refund": 41.57,
        "discount": 141.27,
        "adj_amount": 92.15,
        "total": 81644.73
    },
    {
        "id": 41,
        "srno": 41,
        "month": "Jul",
        "total_orders": 47,
        "subtotal": 48890,
        "tax": 4736.26,
        "shipping": 4.55,
        "refund": 208.82,
        "discount": 244.05,
        "adj_amount": 199.37,
        "total": 53377.31
    },
    {
        "id": 42,
        "srno": 42,
        "month": "Nov",
        "total_orders": 46,
        "subtotal": 57379,
        "tax": 3804.6,
        "shipping": 8.81,
        "refund": 178.33,
        "discount": 42.38,
        "adj_amount": 106.16,
        "total": 61077.86
    },
    {
        "id": 43,
        "srno": 43,
        "month": "Mar",
        "total_orders": 23,
        "subtotal": 86074,
        "tax": 7342.39,
        "shipping": 8.23,
        "refund": 132.14,
        "discount": 251.21,
        "adj_amount": 163.03,
        "total": 93204.3
    },
    {
        "id": 44,
        "srno": 44,
        "month": "Jun",
        "total_orders": 46,
        "subtotal": 63019,
        "tax": 4861.54,
        "shipping": 31.29,
        "refund": 319.72,
        "discount": 259.02,
        "adj_amount": 178.76,
        "total": 67511.85
    },
    {
        "id": 45,
        "srno": 45,
        "month": "Jul",
        "total_orders": 17,
        "subtotal": 49978,
        "tax": 4390.16,
        "shipping": 8.25,
        "refund": 499.07,
        "discount": 197.53,
        "adj_amount": 107.36,
        "total": 53787.17
    },
    {
        "id": 46,
        "srno": 46,
        "month": "Dec",
        "total_orders": 38,
        "subtotal": 77519,
        "tax": 5519.68,
        "shipping": 16.62,
        "refund": 234.47,
        "discount": 67.97,
        "adj_amount": 119.41,
        "total": 82872.27
    },
    {
        "id": 47,
        "srno": 47,
        "month": "Mar",
        "total_orders": 33,
        "subtotal": 28626,
        "tax": 2683.95,
        "shipping": 14.27,
        "refund": 278.43,
        "discount": 135.84,
        "adj_amount": 163.24,
        "total": 31073.19
    },
    {
        "id": 48,
        "srno": 48,
        "month": "Feb",
        "total_orders": 37,
        "subtotal": 26786,
        "tax": 987.13,
        "shipping": 45.77,
        "refund": 324.15,
        "discount": 95.69,
        "adj_amount": 114.68,
        "total": 27513.74
    },
    {
        "id": 49,
        "srno": 49,
        "month": "Nov",
        "total_orders": 39,
        "subtotal": 61762,
        "tax": 1748.06,
        "shipping": 0.67,
        "refund": 373.07,
        "discount": 96.89,
        "adj_amount": 176.42,
        "total": 63217.19
    },
    {
        "id": 50,
        "srno": 50,
        "month": "Jul",
        "total_orders": 11,
        "subtotal": 71807,
        "tax": 4799.87,
        "shipping": 19.17,
        "refund": 289.98,
        "discount": 246.97,
        "adj_amount": 38.34,
        "total": 76127.43
    },
    {
        "id": 51,
        "srno": 51,
        "month": "Jan",
        "total_orders": 31,
        "subtotal": 83259,
        "tax": 3632.23,
        "shipping": 17.49,
        "refund": 137.02,
        "discount": 124.31,
        "adj_amount": 168.97,
        "total": 86816.36
    },
    {
        "id": 52,
        "srno": 52,
        "month": "Sep",
        "total_orders": 12,
        "subtotal": 47823,
        "tax": 2528.69,
        "shipping": 24.71,
        "refund": 309.31,
        "discount": 282.79,
        "adj_amount": 199.8,
        "total": 49984.1
    },
    {
        "id": 53,
        "srno": 53,
        "month": "Jul",
        "total_orders": 41,
        "subtotal": 97544,
        "tax": 5006.32,
        "shipping": 46.0,
        "refund": 460.52,
        "discount": 8.32,
        "adj_amount": 59.14,
        "total": 102186.62
    },
    {
        "id": 54,
        "srno": 54,
        "month": "Feb",
        "total_orders": 16,
        "subtotal": 47352,
        "tax": 4163.01,
        "shipping": 37.87,
        "refund": 150.03,
        "discount": 217.2,
        "adj_amount": 75.63,
        "total": 51261.28
    },
    {
        "id": 55,
        "srno": 55,
        "month": "Dec",
        "total_orders": 48,
        "subtotal": 82514,
        "tax": 3786.67,
        "shipping": 18.83,
        "refund": 363.9,
        "discount": 199.59,
        "adj_amount": 28.03,
        "total": 85784.04
    },
    {
        "id": 56,
        "srno": 56,
        "month": "Mar",
        "total_orders": 29,
        "subtotal": 16910,
        "tax": 1515.49,
        "shipping": 16.79,
        "refund": 9.72,
        "discount": 0.03,
        "adj_amount": 132.74,
        "total": 18565.27
    },
    {
        "id": 57,
        "srno": 57,
        "month": "May",
        "total_orders": 44,
        "subtotal": 57543,
        "tax": 2061.42,
        "shipping": 14.77,
        "refund": 268.45,
        "discount": 187.49,
        "adj_amount": 166.16,
        "total": 59329.41
    },
    {
        "id": 58,
        "srno": 58,
        "month": "Jun",
        "total_orders": 43,
        "subtotal": 63567,
        "tax": 2411.66,
        "shipping": 4.93,
        "refund": 168.63,
        "discount": 257.61,
        "adj_amount": 13.45,
        "total": 65570.8
    },
    {
        "id": 59,
        "srno": 59,
        "month": "Apr",
        "total_orders": 12,
        "subtotal": 54802,
        "tax": 1562.43,
        "shipping": 34.17,
        "refund": 116.31,
        "discount": 157.45,
        "adj_amount": 1.11,
        "total": 56125.95
    },
    {
        "id": 60,
        "srno": 60,
        "month": "Dec",
        "total_orders": 38,
        "subtotal": 98263,
        "tax": 3890.27,
        "shipping": 25.68,
        "refund": 11.13,
        "discount": 42.13,
        "adj_amount": 40.72,
        "total": 102166.41
    },
    {
        "id": 61,
        "srno": 61,
        "month": "Apr",
        "total_orders": 15,
        "subtotal": 94502,
        "tax": 4257.99,
        "shipping": 9.65,
        "refund": 11.65,
        "discount": 134.81,
        "adj_amount": 62.09,
        "total": 98685.27
    },
    {
        "id": 62,
        "srno": 62,
        "month": "Sep",
        "total_orders": 44,
        "subtotal": 49340,
        "tax": 2444.49,
        "shipping": 25.34,
        "refund": 80.2,
        "discount": 237.36,
        "adj_amount": 132.2,
        "total": 51624.47
    },
    {
        "id": 63,
        "srno": 63,
        "month": "Nov",
        "total_orders": 33,
        "subtotal": 65453,
        "tax": 2593.98,
        "shipping": 36.35,
        "refund": 100.7,
        "discount": 143.72,
        "adj_amount": 122.39,
        "total": 67961.3
    },
    {
        "id": 64,
        "srno": 64,
        "month": "Apr",
        "total_orders": 10,
        "subtotal": 35800,
        "tax": 2925.21,
        "shipping": 49.26,
        "refund": 390.1,
        "discount": 16.37,
        "adj_amount": 189.01,
        "total": 38557.01
    },
    {
        "id": 65,
        "srno": 65,
        "month": "Apr",
        "total_orders": 40,
        "subtotal": 74042,
        "tax": 3056.67,
        "shipping": 48.81,
        "refund": 325.9,
        "discount": 236.23,
        "adj_amount": 11.1,
        "total": 76596.45
    },
    {
        "id": 66,
        "srno": 66,
        "month": "Mar",
        "total_orders": 16,
        "subtotal": 13491,
        "tax": 1232.64,
        "shipping": 1.45,
        "refund": 492.1,
        "discount": 71.41,
        "adj_amount": 66.27,
        "total": 14227.85
    },
    {
        "id": 67,
        "srno": 67,
        "month": "Dec",
        "total_orders": 10,
        "subtotal": 30079,
        "tax": 2114.37,
        "shipping": 31.91,
        "refund": 387.28,
        "discount": 16.24,
        "adj_amount": 41.93,
        "total": 31863.69
    },
    {
        "id": 68,
        "srno": 68,
        "month": "Sep",
        "total_orders": 38,
        "subtotal": 63215,
        "tax": 1511.34,
        "shipping": 11.57,
        "refund": 59.79,
        "discount": 175.96,
        "adj_amount": 171.3,
        "total": 64673.46
    },
    {
        "id": 69,
        "srno": 69,
        "month": "Jun",
        "total_orders": 40,
        "subtotal": 45060,
        "tax": 2762.98,
        "shipping": 15.99,
        "refund": 183.76,
        "discount": 5.72,
        "adj_amount": 75.18,
        "total": 47724.67
    },
    {
        "id": 70,
        "srno": 70,
        "month": "Oct",
        "total_orders": 41,
        "subtotal": 10712,
        "tax": 644.77,
        "shipping": 23.12,
        "refund": 67.62,
        "discount": 269.96,
        "adj_amount": 18.96,
        "total": 11061.27
    },
    {
        "id": 71,
        "srno": 71,
        "month": "Nov",
        "total_orders": 23,
        "subtotal": 48414,
        "tax": 3744.84,
        "shipping": 24.78,
        "refund": 107.57,
        "discount": 5.97,
        "adj_amount": 71.53,
        "total": 52141.61
    },
    {
        "id": 72,
        "srno": 72,
        "month": "Nov",
        "total_orders": 41,
        "subtotal": 21017,
        "tax": 1195.18,
        "shipping": 30.93,
        "refund": 278.41,
        "discount": 271.36,
        "adj_amount": 80.45,
        "total": 21773.79
    },
    {
        "id": 73,
        "srno": 73,
        "month": "Jul",
        "total_orders": 15,
        "subtotal": 18646,
        "tax": 1856.77,
        "shipping": 20.72,
        "refund": 332.93,
        "discount": 67.52,
        "adj_amount": 56.66,
        "total": 20179.7
    },
    {
        "id": 74,
        "srno": 74,
        "month": "Jan",
        "total_orders": 11,
        "subtotal": 41780,
        "tax": 4116.37,
        "shipping": 12.1,
        "refund": 200.5,
        "discount": 198.2,
        "adj_amount": 191.84,
        "total": 45701.61
    },
    {
        "id": 75,
        "srno": 75,
        "month": "Oct",
        "total_orders": 19,
        "subtotal": 68326,
        "tax": 5672.19,
        "shipping": 37.91,
        "refund": 351.92,
        "discount": 130.4,
        "adj_amount": 118.86,
        "total": 73672.64
    },
    {
        "id": 76,
        "srno": 76,
        "month": "Dec",
        "total_orders": 41,
        "subtotal": 86370,
        "tax": 7402.44,
        "shipping": 46.66,
        "refund": 372.75,
        "discount": 168.82,
        "adj_amount": 179.88,
        "total": 93457.41
    },
    {
        "id": 77,
        "srno": 77,
        "month": "Dec",
        "total_orders": 14,
        "subtotal": 27665,
        "tax": 1925.75,
        "shipping": 7.13,
        "refund": 185.71,
        "discount": 249.86,
        "adj_amount": 147.67,
        "total": 29309.98
    },
    {
        "id": 78,
        "srno": 78,
        "month": "Nov",
        "total_orders": 19,
        "subtotal": 99539,
        "tax": 2923.2,
        "shipping": 29.34,
        "refund": 391.4,
        "discount": 293.31,
        "adj_amount": 75.58,
        "total": 101882.41
    },
    {
        "id": 79,
        "srno": 79,
        "month": "Apr",
        "total_orders": 50,
        "subtotal": 43339,
        "tax": 1391.19,
        "shipping": 26.89,
        "refund": 123.17,
        "discount": 105.32,
        "adj_amount": 13.99,
        "total": 44542.58
    },
    {
        "id": 80,
        "srno": 80,
        "month": "Nov",
        "total_orders": 43,
        "subtotal": 11685,
        "tax": 1077.43,
        "shipping": 14.07,
        "refund": 374.94,
        "discount": 287.84,
        "adj_amount": 76.55,
        "total": 12190.27
    },
    {
        "id": 81,
        "srno": 81,
        "month": "May",
        "total_orders": 25,
        "subtotal": 10352,
        "tax": 337.53,
        "shipping": 31.47,
        "refund": 115.91,
        "discount": 135.04,
        "adj_amount": 75.08,
        "total": 10545.13
    },
    {
        "id": 82,
        "srno": 82,
        "month": "Sep",
        "total_orders": 30,
        "subtotal": 90012,
        "tax": 6707.12,
        "shipping": 1.94,
        "refund": 200.52,
        "discount": 148.32,
        "adj_amount": 112.25,
        "total": 96484.47
    },
    {
        "id": 83,
        "srno": 83,
        "month": "Aug",
        "total_orders": 50,
        "subtotal": 90977,
        "tax": 6720.2,
        "shipping": 10.48,
        "refund": 489.42,
        "discount": 91.21,
        "adj_amount": 36.16,
        "total": 97163.21
    },
    {
        "id": 84,
        "srno": 84,
        "month": "Apr",
        "total_orders": 31,
        "subtotal": 16193,
        "tax": 637.25,
        "shipping": 6.99,
        "refund": 154.65,
        "discount": 8.77,
        "adj_amount": 69.23,
        "total": 16743.05
    },
    {
        "id": 85,
        "srno": 85,
        "month": "Jan",
        "total_orders": 15,
        "subtotal": 77151,
        "tax": 6597.61,
        "shipping": 30.48,
        "refund": 390.1,
        "discount": 118.06,
        "adj_amount": 193.68,
        "total": 83464.61
    },
    {
        "id": 86,
        "srno": 86,
        "month": "Dec",
        "total_orders": 47,
        "subtotal": 21326,
        "tax": 1893.13,
        "shipping": 24.72,
        "refund": 456.88,
        "discount": 145.51,
        "adj_amount": 162.7,
        "total": 22804.16
    },
    {
        "id": 87,
        "srno": 87,
        "month": "Apr",
        "total_orders": 35,
        "subtotal": 38365,
        "tax": 1407.86,
        "shipping": 5.91,
        "refund": 498.14,
        "discount": 268.32,
        "adj_amount": 62.14,
        "total": 39074.45
    },
    {
        "id": 88,
        "srno": 88,
        "month": "Jan",
        "total_orders": 11,
        "subtotal": 97065,
        "tax": 5884.52,
        "shipping": 33.0,
        "refund": 119.47,
        "discount": 46.87,
        "adj_amount": 126.04,
        "total": 102942.22
    },
    {
        "id": 89,
        "srno": 89,
        "month": "Jun",
        "total_orders": 18,
        "subtotal": 63480,
        "tax": 2480.44,
        "shipping": 24.61,
        "refund": 113.98,
        "discount": 283.14,
        "adj_amount": 38.24,
        "total": 65626.17
    },
    {
        "id": 90,
        "srno": 90,
        "month": "Sep",
        "total_orders": 22,
        "subtotal": 70973,
        "tax": 2721.05,
        "shipping": 23.11,
        "refund": 315.53,
        "discount": 286.43,
        "adj_amount": 83.3,
        "total": 73198.5
    },
    {
        "id": 91,
        "srno": 91,
        "month": "Apr",
        "total_orders": 31,
        "subtotal": 81610,
        "tax": 1661.0,
        "shipping": 1.72,
        "refund": 364.75,
        "discount": 122.07,
        "adj_amount": 10.47,
        "total": 82796.37
    },
    {
        "id": 92,
        "srno": 92,
        "month": "Oct",
        "total_orders": 43,
        "subtotal": 53694,
        "tax": 3377.42,
        "shipping": 36.33,
        "refund": 121.22,
        "discount": 69.98,
        "adj_amount": 96.48,
        "total": 57013.03
    },
    {
        "id": 93,
        "srno": 93,
        "month": "Aug",
        "total_orders": 22,
        "subtotal": 77956,
        "tax": 2007.88,
        "shipping": 20.53,
        "refund": 490.34,
        "discount": 149.99,
        "adj_amount": 146.52,
        "total": 79490.6
    },
    {
        "id": 94,
        "srno": 94,
        "month": "Jan",
        "total_orders": 26,
        "subtotal": 31004,
        "tax": 3092.31,
        "shipping": 0.3,
        "refund": 53.56,
        "discount": 223.29,
        "adj_amount": 60.98,
        "total": 33880.74
    },
    {
        "id": 95,
        "srno": 95,
        "month": "Nov",
        "total_orders": 45,
        "subtotal": 47358,
        "tax": 3733.9,
        "shipping": 24.94,
        "refund": 84.97,
        "discount": 231.14,
        "adj_amount": 8.41,
        "total": 50809.14
    },
    {
        "id": 96,
        "srno": 96,
        "month": "Jan",
        "total_orders": 28,
        "subtotal": 95180,
        "tax": 6234.88,
        "shipping": 38.6,
        "refund": 310.59,
        "discount": 17.74,
        "adj_amount": 163.13,
        "total": 101288.28
    },
    {
        "id": 97,
        "srno": 97,
        "month": "Aug",
        "total_orders": 50,
        "subtotal": 30374,
        "tax": 1496.2,
        "shipping": 38.94,
        "refund": 223.99,
        "discount": 173.14,
        "adj_amount": 40.41,
        "total": 31552.42
    },
    {
        "id": 98,
        "srno": 98,
        "month": "Oct",
        "total_orders": 28,
        "subtotal": 38104,
        "tax": 2086.04,
        "shipping": 42.27,
        "refund": 74.27,
        "discount": 60.27,
        "adj_amount": 186.48,
        "total": 40284.25
    },
    {
        "id": 99,
        "srno": 99,
        "month": "Jul",
        "total_orders": 37,
        "subtotal": 50538,
        "tax": 2300.64,
        "shipping": 8.27,
        "refund": 295.21,
        "discount": 235.98,
        "adj_amount": 14.45,
        "total": 52330.17
    },
    {
        "id": 100,
        "srno": 100,
        "month": "Sep",
        "total_orders": 49,
        "subtotal": 65644,
        "tax": 3765.61,
        "shipping": 30.56,
        "refund": 231.71,
        "discount": 143.65,
        "adj_amount": 56.15,
        "total": 69120.96
    }
]