{
    "data": [
        {
            "first_name": "Venom",
            "last_name": "Devid",
            "email": "devideyopmail.com",
            "phone": "9993333939",
            "created_date": "09/02/2024 09:51 AM",
            "logo": "https://storagemedia.corporategear.com/betastoragemedia/1/store/logo_7.png"
        },
        {
            "first_name": "Venom",
            "last_name": "Devid",
            "email": "devideyopmail.com",
            "phone": "9993333939",
            "created_date": "09/02/2024 09:49 AM",
            "logo": "https://storagemedia.corporategear.com/betastoragemedia/1/store/logo_7.png"
        },
        {
            "first_name": "Venom",
            "last_name": "Devid",
            "email": "devideyopmail.com",
            "phone": "9993333939",
            "created_date": "09/02/2024 09:47 AM",
            "logo": "https://storagemedia.corporategear.com/betastoragemedia/1/store/logo_7.png"
        },
        {
            "first_name": "Venom",
            "last_name": "Devid",
            "email": "devideyopmail.com",
            "phone": "9993333939",
            "created_date": "09/02/2024 09:44 AM",
            "logo": "https://storagemedia.corporategear.com/betastoragemedia/1/store/logo_7.png"
        },
        {
            "first_name": "Venom",
            "last_name": "Devid",
            "email": "devideyopmail.com",
            "phone": "9993333939",
            "created_date": "09/02/2024 09:41 AM",
            "logo": "https://storagemedia.corporategear.com/betastoragemedia/1/store/logo_7.png"
        },
        {
            "first_name": "Venom",
            "last_name": "Devid",
            "email": "devideyopmail.com",
            "phone": "9993333939",
            "created_date": "09/02/2024 09:40 AM",
            "logo": "https://storagemedia.corporategear.com/betastoragemedia/1/store/logo_7.png"
        },
        {
            "first_name": "Venom",
            "last_name": "Devid",
            "email": "devideyopmail.com",
            "phone": "9993333939",
            "created_date": "09/02/2024 09:38 AM",
            "logo": "https://storagemedia.corporategear.com/betastoragemedia/1/store/logo_7.png"
        },
        {
            "first_name": "Venom",
            "last_name": "Devid",
            "email": "devideyopmail.com",
            "phone": "9993333939",
            "created_date": "09/02/2024 09:36 AM",
            "logo": "https://storagemedia.corporategear.com/betastoragemedia/1/store/logo_7.png"
        }
    ]
}