{
  "success": true,
  "data": [
    {
      "id": 19033,
      "productImage": "/betastoragemedia/1/mastercatalog/attributeimages/hu1p009as-wht.jpg",
      "productId": 272,
      "ourSKU": "HU1P009AS-WHT-MISC",
      "name": "White / MISC",
      "recStatus": "active",
      "upc": "1234567890",
      "price": 0.0,
      "createdDate": "2023-05-27T06:16:23.0066667",

      "createdBy": "Shrey Patel",
      "modifiedDate": "2023-05-27T06:16:43.7166667",
      "modifiedBy": "Shrey Patel",
      "location": "313,18596",
      "ipAddress": "",
      "macAddress": "",
      "lastNavSyncDate": "1900-01-01T00:00:00",
      "navSyncStatus": null,
      "isCloned": false,
      "rowVersion": "suvUh6yg3Ag=",
      "quantity": 0,
      "storeLogoUrl": null,
      "displayOrderSize": 999,
      "displayOrderColor": 6,
      "attributeOptionColor": "White"
    },
    {
      "id": 19034,
      "productImage": "/betastoragemedia/1/mastercatalog/attributeimages/hu1p009as-blk.jpg",
      "productId": 272,
      "ourSKU": "HU1P009AS-BLK-MISC",
      "name": "Black / MISC",
      "recStatus": "inactive",
      "upc": "1234567890",

      "price": 0.0,
      "createdDate": "2023-05-27T06:16:23.0066667",
      "createdBy": "Shrey Patel",
      "modifiedDate": "2023-05-27T06:16:43.7166667",
      "modifiedBy": "Shrey Patel",
      "location": "313,18596",
      "ipAddress": "",
      "macAddress": "",
      "lastNavSyncDate": "1900-01-01T00:00:00",
      "navSyncStatus": null,
      "isCloned": false,
      "rowVersion": "suvUh6yg3Ag=",
      "quantity": 0,
      "storeLogoUrl": null,
      "displayOrderSize": 999,
      "displayOrderColor": 6,
      "attributeOptionColor": "Black"
    },
    {
      "id": 19034,
      "productImage": "/betastoragemedia/1/mastercatalog/attributeimages/hu1p009as-red.jpg",
      "productId": 272,
      "ourSKU": "HU1P009AS-RED-MISC",
      "name": "Red / MISC",
      "recStatus": "draft",
      "upc": "1234567890",

      "price": 0.0,
      "createdDate": "2023-05-27T06:16:23.0066667",
      "createdBy": "Vishal Patel",
      "modifiedDate": "2023-05-27T06:16:43.7166667",
      "modifiedBy": "Vishal Patel",
      "location": "313,18596",
      "ipAddress": "",
      "macAddress": "",
      "lastNavSyncDate": "1900-01-01T00:00:00",
      "navSyncStatus": null,
      "isCloned": false,
      "rowVersion": "suvUh6yg3Ag=",
      "quantity": 0,
      "storeLogoUrl": null,
      "displayOrderSize": 999,
      "displayOrderColor": 6,
      "attributeOptionColor": "Red"
    }
  ],
  "errors": {},
  "otherData": null
}
